Workbook

Sheet Raw Data
A1: Transaction_ID | B1: Date | C1: Customer_ID | D1: Customer_Name | E1: Product_ID | F1: Product_Name | G1: Category | H1: Quantity | I1: Unit_Price | J1: Payment_Method | K1: Region | L1: Customer_Segment | M1: Customer_Since | N1: Total_Amount
A2: TRX0155 | B2: 45393 | C2: CUST023 | D2: Paul Baker | E2: P009 | F2: Monitor | G2: Electronics | H2: 3 | I2: 249.99 | J2: Cash | K2: Central | L2: Basic | M2: 44425 | N2: 749.97
A3: TRX0023 | B3: 45396 | C3: CUST013 | D3: Joseph Jackson | E3: P009 | F3: Monitor | G3: Electronics | H3: 3 | I3: 249.99 | J3: Credit Card | K3: Central | L3: Premium | M3: 44575 | N3: 749.97
A4: TRX0139 | B4: 45399 | C4: CUST021 | D4: Kevin Scott | E4: P005 | F4: Blender | G4: Appliances | H4: 3 | I4: 59.99 | J4: PayPal | K4: South | L4: Standard | M4: 45262 | N4: 179.97
A5: TRX0043 | B5: 45400 | C5: CUST046 | D5: Kathleen Bennett | E5: P005 | F5: Blender | G5: Appliances | H5: 3 | I5: 59.99 | J5: Cash | K5: North | L5: Premium | M5: 45114 | N5: 179.97
A6: TRX0212 | B6: 45400 | C6: CUST003 | D6: Michael Brown | E6: P008 | F6: Bookshelf | G6: Furniture | H6: 5 | I6: 149.99 | J6: Credit Card | K6: North | L6: Premium | M6: 45295 | N6: 749.95
A7: TRX0092 | B7: 45403 | C7: CUST024 | D7: Dorothy Nelson | E7: P005 | F7: Blender | G7: Appliances | H7: 2 | I7: 59.99 | J7: Cash | K7: West | L7: Standard | M7: 44746 | N7: 119.98
A8: TRX0193 | B8: 45403 | C8: CUST024 | D8: Dorothy Nelson | E8: P003 | F8: Headphones | G8: Electronics | H8: 5 | I8: 149.99 | J8: Credit Card | K8: Central | L8: Standard | M8: 44418 | N8: 749.95
A9: TRX0240 | B9: 45403 | C9: CUST017 | D9: Charles Allen | E9: P005 | F9: Blender | G9: Appliances | H9: 3 | I9: 59.99 | J9: Debit Card | K9: South | L9: Basic | M9: 45007 | N9: 179.97
A10: TRX0135 | B10: 45405 | C10: CUST009 | D10: Robert Thomas | E10: P001 | F10: Laptop | G10: Electronics | H10: 3 | I10: 899.99 | J10: PayPal | K10: East | L10: Standard | M10: 45299 | N10: 2699.97
A11: TRX0185 | B11: 45408 | C11: CUST026 | D11: Karen Hill | E11: P005 | F11: Blender | G11: Appliances | H11: 3 | I11: 59.99 | J11: Cash | K11: West | L11: Premium | M11: 45207 | N11: 179.97
A12: TRX0138 | B12: 45408 | C12: CUST022 | D12: Susan Green | E12: P008 | F12: Bookshelf | G12: Furniture | H12: 1 | I12: 149.99 | J12: Credit Card | K12: West | L12: Standard | M12: 45103 | N12: 149.99
A13: TRX0209 | B13: 45408 | C13: CUST046 | D13: Kathleen Bennett | E13: P008 | F13: Bookshelf | G13: Furniture | H13: 5 | I13: 149.99 | J13: Debit Card | K13: North | L13: Basic | M13: 44830 | N13: 749.95
... A251: TRX0064 | B251: 45758 | C251: CUST031 | D251: Steven Turner | E251: P010 | F251: Keyboard | G251: Electronics | H251: 3 | I251: 89.99 | J251: Debit Card | K251: North | L251: Premium | M251: 44878 | N251: 269.97

Sheet Analysis
A1: Data Intelligence Dashboard — Analysis
T2: =IF(AND('Raw Data'!G2=$B$17,'Raw Data'!K2=$E$17,'Raw Data'!N2>=$B$18),SUMPRODUCT(('Raw Data'!$G$2:$G2=$B$17)*('Raw Data'!$K$2:$K2=$E$17)*('Raw Data'!$N$2:$N2>=$B$18)),"")
A3: A. Date & Time Intelligence | T3: =IF(AND('Raw Data'!G3=$B$17,'Raw Data'!K3=$E$17,'Raw Data'!N3>=$B$18),SUMPRODUCT(('Raw Data'!$G$2:$G3=$B$17)*('Raw Data'!$K$2:$K3=$E$17)*('Raw Data'!$N$2:$N3>=$B$18)),"")
A4: Report Generated (NOW) | B4: =NOW() -> 46288.474 | T4: =IF(AND('Raw Data'!G4=$B$17,'Raw Data'!K4=$E$17,'Raw Data'!N4>=$B$18),SUMPRODUCT(('Raw Data'!$G$2:$G4=$B$17)*('Raw Data'!$K$2:$K4=$E$17)*('Raw Data'!$N$2:$N4>=$B$18)),"")
A5: Report Date (TODAY) | B5: =TODAY() -> 46288 | T5: =IF(AND('Raw Data'!G5=$B$17,'Raw Data'!K5=$E$17,'Raw Data'!N5>=$B$18),SUMPRODUCT(('Raw Data'!$G$2:$G5=$B$17)*('Raw Data'!$K$2:$K5=$E$17)*('Raw Data'!$N$2:$N5>=$B$18)),"")
A6: First Transaction Date (MIN) | B6: =MIN('Raw Data'!B2:B251) -> 45393 | T6: =IF(AND('Raw Data'!G6=$B$17,'Raw Data'!K6=$E$17,'Raw Data'!N6>=$B$18),SUMPRODUCT(('Raw Data'!$G$2:$G6=$B$17)*('Raw Data'!$K$2:$K6=$E$17)*('Raw Data'!$N$2:$N6>=$B$18)),"")
A7: Last Transaction Date (MAX) | B7: =MAX('Raw Data'!B2:B251) -> 45758 | T7: =IF(AND('Raw Data'!G7=$B$17,'Raw Data'!K7=$E$17,'Raw Data'!N7>=$B$18),SUMPRODUCT(('Raw Data'!$G$2:$G7=$B$17)*('Raw Data'!$K$2:$K7=$E$17)*('Raw Data'!$N$2:$N7>=$B$18)),"")
A8: Days Since Last Transaction (DATEDIF) | B8: =DATEDIF(B7,B5,"d") -> 530 | T8: =IF(AND('Raw Data'!G8=$B$17,'Raw Data'!K8=$E$17,'Raw Data'!N8>=$B$18),SUMPRODUCT(('Raw Data'!$G$2:$G8=$B$17)*('Raw Data'!$K$2:$K8=$E$17)*('Raw Data'!$N$2:$N8>=$B$18)),"")
A9: Data Collection Span (Months, DATEDIF) | B9: =DATEDIF(B6,B7,"m") -> 12 | T9: =IF(AND('Raw Data'!G9=$B$17,'Raw Data'!K9=$E$17,'Raw Data'!N9>=$B$18),SUMPRODUCT(('Raw Data'!$G$2:$G9=$B$17)*('Raw Data'!$K$2:$K9=$E$17)*('Raw Data'!$N$2:$N9>=$B$18)),"")
A10: End of Month — Last Transaction (EOMONTH) | B10: =EOMONTH(B7,0) -> 45777 | T10: =IF(AND('Raw Data'!G10=$B$17,'Raw Data'!K10=$E$17,'Raw Data'!N10>=$B$18),SUMPRODUCT(('Raw Data'!$G$2:$G10=$B$17)*('Raw Data'!$K$2:$K10=$E$17)*('Raw Data'!$N$2:$N10>=$B$18)),"")
A11: Next Reporting Month End (EOMONTH+1) | B11: =EOMONTH(B7,1) -> 45808 | T11: =IF(AND('Raw Data'!G11=$B$17,'Raw Data'!K11=$E$17,'Raw Data'!N11>=$B$18),SUMPRODUCT(('Raw Data'!$G$2:$G11=$B$17)*('Raw Data'!$K$2:$K11=$E$17)*('Raw Data'!$N$2:$N11>=$B$18)),"")
T12: =IF(AND('Raw Data'!G12=$B$17,'Raw Data'!K12=$E$17,'Raw Data'!N12>=$B$18),SUMPRODUCT(('Raw Data'!$G$2:$G12=$B$17)*('Raw Data'!$K$2:$K12=$E$17)*('Raw Data'!$N$2:$N12>=$B$18)),"")
A13: Change-Log Timestamp Demo (iterative calc) | T13: =IF(AND('Raw Data'!G13=$B$17,'Raw Data'!K13=$E$17,'Raw Data'!N13>=$B$18),SUMPRODUCT(('Raw Data'!$G$2:$G13=$B$17)*('Raw Data'!$K$2:$K13=$E$17)*('Raw Data'!$N$2:$N13>=$B$18)),"")
A14: Type anything here → | C14: =IF(B14<>"",IF(C14="",NOW(),C14),"") | D14: ← timestamp locks the instant B is first filled in (Iterative Calculation is enabled in this workbook: File > Options > Formulas > Enable iterative calculation) | T14: =IF(AND('Raw Data'!G14=$B$17,'Raw Data'!K14=$E$17,'Raw Data'!N14>=$B$18),SUMPRODUCT(('Raw Data'!$G$2:$G14=$B$17)*('Raw Data'!$K$2:$K14=$E$17)*('Raw Data'!$N$2:$N14>=$B$18)),"")
T15: =IF(AND('Raw Data'!G15=$B$17,'Raw Data'!K15=$E$17,'Raw Data'!N15>=$B$18),SUMPRODUCT(('Raw Data'!$G$2:$G15=$B$17)*('Raw Data'!$K$2:$K15=$E$17)*('Raw Data'!$N$2:$N15>=$B$18)),"")
A16: B. Multi-Value Search — Extract All Matching Transactions (FILTER-style) | T16: =IF(AND('Raw Data'!G16=$B$17,'Raw Data'!K16=$E$17,'Raw Data'!N16>=$B$18),SUMPRODUCT(('Raw Data'!$G$2:$G16=$B$17)*('Raw Data'!$K$2:$K16=$E$17)*('Raw Data'!$N$2:$N16>=$B$18)),"")
A17: Category: | B17: Electronics | D17: Region: | E17: North | T17: =IF(AND('Raw Data'!G17=$B$17,'Raw Data'!K17=$E$17,'Raw Data'!N17>=$B$18),SUMPRODUCT(('Raw Data'!$G$2:$G17=$B$17)*('Raw Data'!$K$2:$K17=$E$17)*('Raw Data'!$N$2:$N17>=$B$18)),"") -> 1
A18: Min Amount ($): | B18: 500 | D18: ← change any yellow cell; the list below refreshes automatically (equivalent to Excel's dynamic FILTER function) | T18: =IF(AND('Raw Data'!G18=$B$17,'Raw Data'!K18=$E$17,'Raw Data'!N18>=$B$18),SUMPRODUCT(('Raw Data'!$G$2:$G18=$B$17)*('Raw Data'!$K$2:$K18=$E$17)*('Raw Data'!$N$2:$N18>=$B$18)),"")
A19: Transaction_ID | B19: Date | C19: Customer_Name | D19: Product_Name | E19: Region | F19: Category | G19: Total_Amount | T19: =IF(AND('Raw Data'!G19=$B$17,'Raw Data'!K19=$E$17,'Raw Data'!N19>=$B$18),SUMPRODUCT(('Raw Data'!$G$2:$G19=$B$17)*('Raw Data'!$K$2:$K19=$E$17)*('Raw Data'!$N$2:$N19>=$B$18)),"") -> 2
A20: =IFERROR(INDEX('Raw Data'!$A$2:$A$251,MATCH(ROW()-19,$T$2:$T$251,0)),"") -> TRX0230 | B20: =IFERROR(INDEX('Raw Data'!$B$2:$B$251,MATCH(ROW()-19,$T$2:$T$251,0)),"") -> 45409 | C20: =IFERROR(INDEX('Raw Data'!$D$2:$D$251,MATCH(ROW()-19,$T$2:$T$251,0)),"") -> George Adams | D20: =IFERROR(INDEX('Raw Data'!$F$2:$F$251,MATCH(ROW()-19,$T$2:$T$251,0)),"") -> Laptop | E20: =IFERROR(INDEX('Raw Data'!$K$2:$K$251,MATCH(ROW()-19,$T$2:$T$251,0)),"") -> North | F20: =IFERROR(INDEX('Raw Data'!$G$2:$G$251,MATCH(ROW()-19,$T$2:$T$251,0)),"") -> Electronics | G20: =IFERROR(INDEX('Raw Data'!$N$2:$N$251,MATCH(ROW()-19,$T$2:$T$251,0)),"") -> 899.99 | T20: =IF(AND('Raw Data'!G20=$B$17,'Raw Data'!K20=$E$17,'Raw Data'!N20>=$B$18),SUMPRODUCT(('Raw Data'!$G$2:$G20=$B$17)*('Raw Data'!$K$2:$K20=$E$17)*('Raw Data'!$N$2:$N20>=$B$18)),"")
A21: =IFERROR(INDEX('Raw Data'!$A$2:$A$251,MATCH(ROW()-19,$T$2:$T$251,0)),"") -> TRX0134 | B21: =IFERROR(INDEX('Raw Data'!$B$2:$B$251,MATCH(ROW()-19,$T$2:$T$251,0)),"") -> 45410 | C21: =IFERROR(INDEX('Raw Data'!$D$2:$D$251,MATCH(ROW()-19,$T$2:$T$251,0)),"") -> Maria Garcia | D21: =IFERROR(INDEX('Raw Data'!$F$2:$F$251,MATCH(ROW()-19,$T$2:$T$251,0)),"") -> Smartphone | E21: =IFERROR(INDEX('Raw Data'!$K$2:$K$251,MATCH(ROW()-19,$T$2:$T$251,0)),"") -> North | F21: =IFERROR(INDEX('Raw Data'!$G$2:$G$251,MATCH(ROW()-19,$T$2:$T$251,0)),"") -> Electronics | G21: =IFERROR(INDEX('Raw Data'!$N$2:$N$251,MATCH(ROW()-19,$T$2:$T$251,0)),"") -> 1399.98 | T21: =IF(AND('Raw Data'!G21=$B$17,'Raw Data'!K21=$E$17,'Raw Data'!N21>=$B$18),SUMPRODUCT(('Raw Data'!$G$2:$G21=$B$17)*('Raw Data'!$K$2:$K21=$E$17)*('Raw Data'!$N$2:$N21>=$B$18)),"") -> 3
A22: =IFERROR(INDEX('Raw Data'!$A$2:$A$251,MATCH(ROW()-19,$T$2:$T$251,0)),"") -> TRX0222 | B22: =IFERROR(INDEX('Raw Data'!$B$2:$B$251,MATCH(ROW()-19,$T$2:$T$251,0)),"") -> 45410 | C22: =IFERROR(INDEX('Raw Data'!$D$2:$D$251,MATCH(ROW()-19,$T$2:$T$251,0)),"") -> Virginia Sanders | D22: =IFERROR(INDEX('Raw Data'!$F$2:$F$251,MATCH(ROW()-19,$T$2:$T$251,0)),"") -> Monitor | E22: =IFERROR(INDEX('Raw Data'!$K$2:$K$251,MATCH(ROW()-19,$T$2:$T$251,0)),"") -> North | F22: =IFERROR(INDEX('Raw Data'!$G$2:$G$251,MATCH(ROW()-19,$T$2:$T$251,0)),"") -> Electronics | G22: =IFERROR(INDEX('Raw Data'!$N$2:$N$251,MATCH(ROW()-19,$T$2:$T$251,0)),"") -> 749.97 | T22: =IF(AND('Raw Data'!G22=$B$17,'Raw Data'!K22=$E$17,'Raw Data'!N22>=$B$18),SUMPRODUCT(('Raw Data'!$G$2:$G22=$B$17)*('Raw Data'!$K$2:$K22=$E$17)*('Raw Data'!$N$2:$N22>=$B$18)),"")
A23: =IFERROR(INDEX('Raw Data'!$A$2:$A$251,MATCH(ROW()-19,$T$2:$T$251,0)),"") -> TRX0204 | B23: =IFERROR(INDEX('Raw Data'!$B$2:$B$251,MATCH(ROW()-19,$T$2:$T$251,0)),"") -> 45415 | C23: =IFERROR(INDEX('Raw Data'!$D$2:$D$251,MATCH(ROW()-19,$T$2:$T$251,0)),"") -> Cynthia Price | D23: =IFERROR(INDEX('Raw Data'!$F$2:$F$251,MATCH(ROW()-19,$T$2:$T$251,0)),"") -> Monitor | E23: =IFERROR(INDEX('Raw Data'!$K$2:$K$251,MATCH(ROW()-19,$T$2:$T$251,0)),"") -> North | F23: =IFERROR(INDEX('Raw Data'!$G$2:$G$251,MATCH(ROW()-19,$T$2:$T$251,0)),"") -> Electronics | G23: =IFERROR(INDEX('Raw Data'!$N$2:$N$251,MATCH(ROW()-19,$T$2:$T$251,0)),"") -> 999.96 | T23: =IF(AND('Raw Data'!G23=$B$17,'Raw Data'!K23=$E$17,'Raw Data'!N23>=$B$18),SUMPRODUCT(('Raw Data'!$G$2:$G23=$B$17)*('Raw Data'!$K$2:$K23=$E$17)*('Raw Data'!$N$2:$N23>=$B$18)),"")
A24: =IFERROR(INDEX('Raw Data'!$A$2:$A$251,MATCH(ROW()-19,$T$2:$T$251,0)),"") -> TRX0217 | B24: =IFERROR(INDEX('Raw Data'!$B$2:$B$251,MATCH(ROW()-19,$T$2:$T$251,0)),"") -> 45503 | C24: =IFERROR(INDEX('Raw Data'!$D$2:$D$251,MATCH(ROW()-19,$T$2:$T$251,0)),"") -> Mark Carter | D24: =IFERROR(INDEX('Raw Data'!$F$2:$F$251,MATCH(ROW()-19,$T$2:$T$251,0)),"") -> Smartphone | E24: =IFERROR(INDEX('Raw Data'!$K$2:$K$251,MATCH(ROW()-19,$T$2:$T$251,0)),"") -> North | F24: =IFERROR(INDEX('Raw Data'!$G$2:$G$251,MATCH(ROW()-19,$T$2:$T$251,0)),"") -> Electronics | G24: =IFERROR(INDEX('Raw Data'!$N$2:$N$251,MATCH(ROW()-19,$T$2:$T$251,0)),"") -> 1399.98 | T24: =IF(AND('Raw Data'!G24=$B$17,'Raw Data'!K24=$E$17,'Raw Data'!N24>=$B$18),SUMPRODUCT(('Raw Data'!$G$2:$G24=$B$17)*('Raw Data'!$K$2:$K24=$E$17)*('Raw Data'!$N$2:$N24>=$B$18)),"") -> 4
A25: =IFERROR(INDEX('Raw Data'!$A$2:$A$251,MATCH(ROW()-19,$T$2:$T$251,0)),"") -> TRX0098 | B25: =IFERROR(INDEX('Raw Data'!$B$2:$B$251,MATCH(ROW()-19,$T$2:$T$251,0)),"") -> 45517 | C25: =IFERROR(INDEX('Raw Data'!$D$2:$D$251,MATCH(ROW()-19,$T$2:$T$251,0)),"") -> Karen Hill | D25: =IFERROR(INDEX('Raw Data'!$F$2:$F$251,MATCH(ROW()-19,$T$2:$T$251,0)),"") -> Monitor | E25: =IFERROR(INDEX('Raw Data'!$K$2:$K$251,MATCH(ROW()-19,$T$2:$T$251,0)),"") -> North | F25: =IFERROR(INDEX('Raw Data'!$G$2:$G$251,MATCH(ROW()-19,$T$2:$T$251,0)),"") -> Electronics | G25: =IFERROR(INDEX('Raw Data'!$N$2:$N$251,MATCH(ROW()-19,$T$2:$T$251,0)),"") -> 749.97 | T25: =IF(AND('Raw Data'!G25=$B$17,'Raw Data'!K25=$E$17,'Raw Data'!N25>=$B$18),SUMPRODUCT(('Raw Data'!$G$2:$G25=$B$17)*('Raw Data'!$K$2:$K25=$E$17)*('Raw Data'!$N$2:$N25>=$B$18)),"")
A26: =IFERROR(INDEX('Raw Data'!$A$2:$A$251,MATCH(ROW()-19,$T$2:$T$251,0)),"") -> TRX0248 | B26: =IFERROR(INDEX('Raw Data'!$B$2:$B$251,MATCH(ROW()-19,$T$2:$T$251,0)),"") -> 45534 | C26: =IFERROR(INDEX('Raw Data'!$D$2:$D$251,MATCH(ROW()-19,$T$2:$T$251,0)),"") -> Sandra Phillips | D26: =IFERROR(INDEX('Raw Data'!$F$2:$F$251,MATCH(ROW()-19,$T$2:$T$251,0)),"") -> Smartphone | E26: =IFERROR(INDEX('Raw Data'!$K$2:$K$251,MATCH(ROW()-19,$T$2:$T$251,0)),"") -> North | F26: =IFERROR(INDEX('Raw Data'!$G$2:$G$251,MATCH(ROW()-19,$T$2:$T$251,0)),"") -> Electronics | G26: =IFERROR(INDEX('Raw Data'!$N$2:$N$251,MATCH(ROW()-19,$T$2:$T$251,0)),"") -> 1399.98 | T26: =IF(AND('Raw Data'!G26=$B$17,'Raw Data'!K26=$E$17,'Raw Data'!N26>=$B$18),SUMPRODUCT(('Raw Data'!$G$2:$G26=$B$17)*('Raw Data'!$K$2:$K26=$E$17)*('Raw Data'!$N$2:$N26>=$B$18)),"")
A27: =IFERROR(INDEX('Raw Data'!$A$2:$A$251,MATCH(ROW()-19,$T$2:$T$251,0)),"") -> TRX0005 | B27: =IFERROR(INDEX('Raw Data'!$B$2:$B$251,MATCH(ROW()-19,$T$2:$T$251,0)),"") -> 45550 | C27: =IFERROR(INDEX('Raw Data'!$D$2:$D$251,MATCH(ROW()-19,$T$2:$T$251,0)),"") -> Ruth Brooks | D27: =IFERROR(INDEX('Raw Data'!$F$2:$F$251,MATCH(ROW()-19,$T$2:$T$251,0)),"") -> Headphones | E27: =IFERROR(INDEX('Raw Data'!$K$2:$K$251,MATCH(ROW()-19,$T$2:$T$251,0)),"") -> North | F27: =IFERROR(INDEX('Raw Data'!$G$2:$G$251,MATCH(ROW()-19,$T$2:$T$251,0)),"") -> Electronics | G27: =IFERROR(INDEX('Raw Data'!$N$2:$N$251,MATCH(ROW()-19,$T$2:$T$251,0)),"") -> 599.96 | T27: =IF(AND('Raw Data'!G27=$B$17,'Raw Data'!K27=$E$17,'Raw Data'!N27>=$B$18),SUMPRODUCT(('Raw Data'!$G$2:$G27=$B$17)*('Raw Data'!$K$2:$K27=$E$17)*('Raw Data'!$N$2:$N27>=$B$18)),"")
A28: =IFERROR(INDEX('Raw Data'!$A$2:$A$251,MATCH(ROW()-19,$T$2:$T$251,0)),"") -> TRX0177 | B28: =IFERROR(INDEX('Raw Data'!$B$2:$B$251,MATCH(ROW()-19,$T$2:$T$251,0)),"") -> 45559 | C28: =IFERROR(INDEX('Raw Data'!$D$2:$D$251,MATCH(ROW()-19,$T$2:$T$251,0)),"") -> Sandra Phillips | D28: =IFERROR(INDEX('Raw Data'!$F$2:$F$251,MATCH(ROW()-19,$T$2:$T$251,0)),"") -> Laptop | E28: =IFERROR(INDEX('Raw Data'!$K$2:$K$251,MATCH(ROW()-19,$T$2:$T$251,0)),"") -> North | F28: =IFERROR(INDEX('Raw Data'!$G$2:$G$251,MATCH(ROW()-19,$T$2:$T$251,0)),"") -> Electronics | G28: =IFERROR(INDEX('Raw Data'!$N$2:$N$251,MATCH(ROW()-19,$T$2:$T$251,0)),"") -> 2699.97 | T28: =IF(AND('Raw Data'!G28=$B$17,'Raw Data'!K28=$E$17,'Raw Data'!N28>=$B$18),SUMPRODUCT(('Raw Data'!$G$2:$G28=$B$17)*('Raw Data'!$K$2:$K28=$E$17)*('Raw Data'!$N$2:$N28>=$B$18)),"")
A29: =IFERROR(INDEX('Raw Data'!$A$2:$A$251,MATCH(ROW()-19,$T$2:$T$251,0)),"") -> TRX0203 | B29: =IFERROR(INDEX('Raw Data'!$B$2:$B$251,MATCH(ROW()-19,$T$2:$T$251,0)),"") -> 45572 | C29: =IFERROR(INDEX('Raw Data'!$D$2:$D$251,MATCH(ROW()-19,$T$2:$T$251,0)),"") -> Sandra Phillips | D29: =IFERROR(INDEX('Raw Data'!$F$2:$F$251,MATCH(ROW()-19,$T$2:$T$251,0)),"") -> Headphones | E29: =IFERROR(INDEX('Raw Data'!$K$2:$K$251,MATCH(ROW()-19,$T$2:$T$251,0)),"") -> North | F29: =IFERROR(INDEX('Raw Data'!$G$2:$G$251,MATCH(ROW()-19,$T$2:$T$251,0)),"") -> Electronics | G29: =IFERROR(INDEX('Raw Data'!$N$2:$N$251,MATCH(ROW()-19,$T$2:$T$251,0)),"") -> 599.96 | T29: =IF(AND('Raw Data'!G29=$B$17,'Raw Data'!K29=$E$17,'Raw Data'!N29>=$B$18),SUMPRODUCT(('Raw Data'!$G$2:$G29=$B$17)*('Raw Data'!$K$2:$K29=$E$17)*('Raw Data'!$N$2:$N29>=$B$18)),"")
A30: =IFERROR(INDEX('Raw Data'!$A$2:$A$251,MATCH(ROW()-19,$T$2:$T$251,0)),"") -> TRX0167 | B30: =IFERROR(INDEX('Raw Data'!$B$2:$B$251,MATCH(ROW()-19,$T$2:$T$251,0)),"") -> 45589 | C30: =IFERROR(INDEX('Raw Data'!$D$2:$D$251,MATCH(ROW()-19,$T$2:$T$251,0)),"") -> Betty Campbell | D30: =IFERROR(INDEX('Raw Data'!$F$2:$F$251,MATCH(ROW()-19,$T$2:$T$251,0)),"") -> Smartphone | E30: =IFERROR(INDEX('Raw Data'!$K$2:$K$251,MATCH(ROW()-19,$T$2:$T$251,0)),"") -> North | F30: =IFERROR(INDEX('Raw Data'!$G$2:$G$251,MATCH(ROW()-19,$T$2:$T$251,0)),"") -> Electronics | G30: =IFERROR(INDEX('Raw Data'!$N$2:$N$251,MATCH(ROW()-19,$T$2:$T$251,0)),"") -> 3499.95 | T30: =IF(AND('Raw Data'!G30=$B$17,'Raw Data'!K30=$E$17,'Raw Data'!N30>=$B$18),SUMPRODUCT(('Raw Data'!$G$2:$G30=$B$17)*('Raw Data'!$K$2:$K30=$E$17)*('Raw Data'!$N$2:$N30>=$B$18)),"")
A31: =IFERROR(INDEX('Raw Data'!$A$2:$A$251,MATCH(ROW()-19,$T$2:$T$251,0)),"") -> TRX0012 | B31: =IFERROR(INDEX('Raw Data'!$B$2:$B$251,MATCH(ROW()-19,$T$2:$T$251,0)),"") -> 45622 | C31: =IFERROR(INDEX('Raw Data'!$D$2:$D$251,MATCH(ROW()-19,$T$2:$T$251,0)),"") -> Douglas Watson | D31: =IFERROR(INDEX('Raw Data'!$F$2:$F$251,MATCH(ROW()-19,$T$2:$T$251,0)),"") -> Monitor | E31: =IFERROR(INDEX('Raw Data'!$K$2:$K$251,MATCH(ROW()-19,$T$2:$T$251,0)),"") -> North | F31: =IFERROR(INDEX('Raw Data'!$G$2:$G$251,MATCH(ROW()-19,$T$2:$T$251,0)),"") -> Electronics | G31: =IFERROR(INDEX('Raw Data'!$N$2:$N$251,MATCH(ROW()-19,$T$2:$T$251,0)),"") -> 1249.95 | T31: =IF(AND('Raw Data'!G31=$B$17,'Raw Data'!K31=$E$17,'Raw Data'!N31>=$B$18),SUMPRODUCT(('Raw Data'!$G$2:$G31=$B$17)*('Raw Data'!$K$2:$K31=$E$17)*('Raw Data'!$N$2:$N31>=$B$18)),"")
... A39: =IFERROR(INDEX('Raw Data'!$A$2:$A$251,MATCH(ROW()-19,$T$2:$T$251,0)),"") -> TRX0124 | B39: =IFERROR(INDEX('Raw Data'!$B$2:$B$251,MATCH(ROW()-19,$T$2:$T$251,0)),"") -> 45737 | C39: =IFERROR(INDEX('Raw Data'!$D$2:$D$251,MATCH(ROW()-19,$T$2:$T$251,0)),"") -> Sharon Butler | D39: =IFERROR(INDEX('Raw Data'!$F$2:$F$251,MATCH(ROW()-19,$T$2:$T$251,0)),"") -> Laptop | E39: =IFERROR(INDEX('Raw Data'!$K$2:$K$251,MATCH(ROW()-19,$T$2:$T$251,0)),"") -> North | F39: =IFERROR(INDEX('Raw Data'!$G$2:$G$251,MATCH(ROW()-19,$T$2:$T$251,0)),"") -> Electronics | G39: =IFERROR(INDEX('Raw Data'!$N$2:$N$251,MATCH(ROW()-19,$T$2:$T$251,0)),"") -> 2699.97 | T39: =IF(AND('Raw Data'!G39=$B$17,'Raw Data'!K39=$E$17,'Raw Data'!N39>=$B$18),SUMPRODUCT(('Raw Data'!$G$2:$G39=$B$17)*('Raw Data'!$K$2:$K39=$E$17)*('Raw Data'!$N$2:$N39>=$B$18)),"")
T40: =IF(AND('Raw Data'!G40=$B$17,'Raw Data'!K40=$E$17,'Raw Data'!N40>=$B$18),SUMPRODUCT(('Raw Data'!$G$2:$G40=$B$17)*('Raw Data'!$K$2:$K40=$E$17)*('Raw Data'!$N$2:$N40>=$B$18)),"")
A41: Match count: | B41: =COUNT($T$2:$T$251) -> 23 | T41: =IF(AND('Raw Data'!G41=$B$17,'Raw Data'!K41=$E$17,'Raw Data'!N41>=$B$18),SUMPRODUCT(('Raw Data'!$G$2:$G41=$B$17)*('Raw Data'!$K$2:$K41=$E$17)*('Raw Data'!$N$2:$N41>=$B$18)),"")
T42: =IF(AND('Raw Data'!G42=$B$17,'Raw Data'!K42=$E$17,'Raw Data'!N42>=$B$18),SUMPRODUCT(('Raw Data'!$G$2:$G42=$B$17)*('Raw Data'!$K$2:$K42=$E$17)*('Raw Data'!$N$2:$N42>=$B$18)),"")
T43: =IF(AND('Raw Data'!G43=$B$17,'Raw Data'!K43=$E$17,'Raw Data'!N43>=$B$18),SUMPRODUCT(('Raw Data'!$G$2:$G43=$B$17)*('Raw Data'!$K$2:$K43=$E$17)*('Raw Data'!$N$2:$N43>=$B$18)),"")
A44: C. High-Value Customers — Grouped by Customer (SUMIFS / COUNTIFS / RANK) | T44: =IF(AND('Raw Data'!G44=$B$17,'Raw Data'!K44=$E$17,'Raw Data'!N44>=$B$18),SUMPRODUCT(('Raw Data'!$G$2:$G44=$B$17)*('Raw Data'!$K$2:$K44=$E$17)*('Raw Data'!$N$2:$N44>=$B$18)),"")
A45: Customer_ID | B45: Customer_Name | C45: Segment | D45: Transactions | E45: Total Spent | F45: Avg Order Value | G45: Rank | H45: Top 10 Flag | T45: =IF(AND('Raw Data'!G45=$B$17,'Raw Data'!K45=$E$17,'Raw Data'!N45>=$B$18),SUMPRODUCT(('Raw Data'!$G$2:$G45=$B$17)*('Raw Data'!$K$2:$K45=$E$17)*('Raw Data'!$N$2:$N45>=$B$18)),"") | U45: PremRank(helper)
A46: CUST001 | B46: John Smith | C46: =INDEX('Raw Data'!$L$2:$L$251,MATCH(A46,'Raw Data'!$C$2:$C$251,0)) -> Standard | D46: =COUNTIFS('Raw Data'!$C$2:$C$251,A46) -> 1 | E46: =SUMIFS('Raw Data'!$N$2:$N$251,'Raw Data'!$C$2:$C$251,A46) -> 599.96 | F46: =IFERROR(E46/D46,0) -> 599.96 | G46: =RANK(E46,$E$46:$E$95) -> 47 | H46: =IF(G46<=10,"⭐ Top 10","") | T46: =IF(AND('Raw Data'!G46=$B$17,'Raw Data'!K46=$E$17,'Raw Data'!N46>=$B$18),SUMPRODUCT(('Raw Data'!$G$2:$G46=$B$17)*('Raw Data'!$K$2:$K46=$E$17)*('Raw Data'!$N$2:$N46>=$B$18)),"") | U46: =IF($C46="Premium",SUMPRODUCT(($C$46:$C46="Premium")*1),"")
A47: CUST002 | B47: Emma Wilson | C47: =INDEX('Raw Data'!$L$2:$L$251,MATCH(A47,'Raw Data'!$C$2:$C$251,0)) -> Premium | D47: =COUNTIFS('Raw Data'!$C$2:$C$251,A47) -> 5 | E47: =SUMIFS('Raw Data'!$N$2:$N$251,'Raw Data'!$C$2:$C$251,A47) -> 1229.88 | F47: =IFERROR(E47/D47,0) -> 245.976 | G47: =RANK(E47,$E$46:$E$95) -> 44 | H47: =IF(G47<=10,"⭐ Top 10","") | T47: =IF(AND('Raw Data'!G47=$B$17,'Raw Data'!K47=$E$17,'Raw Data'!N47>=$B$18),SUMPRODUCT(('Raw Data'!$G$2:$G47=$B$17)*('Raw Data'!$K$2:$K47=$E$17)*('Raw Data'!$N$2:$N47>=$B$18)),"") | U47: =IF($C47="Premium",SUMPRODUCT(($C$46:$C47="Premium")*1),"") -> 1
A48: CUST003 | B48: Michael Brown | C48: =INDEX('Raw Data'!$L$2:$L$251,MATCH(A48,'Raw Data'!$C$2:$C$251,0)) -> Premium | D48: =COUNTIFS('Raw Data'!$C$2:$C$251,A48) -> 9 | E48: =SUMIFS('Raw Data'!$N$2:$N$251,'Raw Data'!$C$2:$C$251,A48) -> 6169.74 | F48: =IFERROR(E48/D48,0) -> 685.52667 | G48: =RANK(E48,$E$46:$E$95) -> 14 | H48: =IF(G48<=10,"⭐ Top 10","") | T48: =IF(AND('Raw Data'!G48=$B$17,'Raw Data'!K48=$E$17,'Raw Data'!N48>=$B$18),SUMPRODUCT(('Raw Data'!$G$2:$G48=$B$17)*('Raw Data'!$K$2:$K48=$E$17)*('Raw Data'!$N$2:$N48>=$B$18)),"") | U48: =IF($C48="Premium",SUMPRODUCT(($C$46:$C48="Premium")*1),"") -> 2
A49: CUST004 | B49: Sarah Davis | C49: =INDEX('Raw Data'!$L$2:$L$251,MATCH(A49,'Raw Data'!$C$2:$C$251,0)) -> Standard | D49: =COUNTIFS('Raw Data'!$C$2:$C$251,A49) -> 5 | E49: =SUMIFS('Raw Data'!$N$2:$N$251,'Raw Data'!$C$2:$C$251,A49) -> 5499.81 | F49: =IFERROR(E49/D49,0) -> 1099.962 | G49: =RANK(E49,$E$46:$E$95) -> 19 | H49: =IF(G49<=10,"⭐ Top 10","") | T49: =IF(AND('Raw Data'!G49=$B$17,'Raw Data'!K49=$E$17,'Raw Data'!N49>=$B$18),SUMPRODUCT(('Raw Data'!$G$2:$G49=$B$17)*('Raw Data'!$K$2:$K49=$E$17)*('Raw Data'!$N$2:$N49>=$B$18)),"") | U49: =IF($C49="Premium",SUMPRODUCT(($C$46:$C49="Premium")*1),"")
A50: CUST005 | B50: James Johnson | C50: =INDEX('Raw Data'!$L$2:$L$251,MATCH(A50,'Raw Data'!$C$2:$C$251,0)) -> Premium | D50: =COUNTIFS('Raw Data'!$C$2:$C$251,A50) -> 1 | E50: =SUMIFS('Raw Data'!$N$2:$N$251,'Raw Data'!$C$2:$C$251,A50) -> 179.97 | F50: =IFERROR(E50/D50,0) -> 179.97 | G50: =RANK(E50,$E$46:$E$95) -> 50 | H50: =IF(G50<=10,"⭐ Top 10","") | T50: =IF(AND('Raw Data'!G50=$B$17,'Raw Data'!K50=$E$17,'Raw Data'!N50>=$B$18),SUMPRODUCT(('Raw Data'!$G$2:$G50=$B$17)*('Raw Data'!$K$2:$K50=$E$17)*('Raw Data'!$N$2:$N50>=$B$18)),"") | U50: =IF($C50="Premium",SUMPRODUCT(($C$46:$C50="Premium")*1),"") -> 3
A51: CUST006 | B51: Lisa Anderson | C51: =INDEX('Raw Data'!$L$2:$L$251,MATCH(A51,'Raw Data'!$C$2:$C$251,0)) -> Basic | D51: =COUNTIFS('Raw Data'!$C$2:$C$251,A51) -> 5 | E51: =SUMIFS('Raw Data'!$N$2:$N$251,'Raw Data'!$C$2:$C$251,A51) -> 2039.8 | F51: =IFERROR(E51/D51,0) -> 407.96 | G51: =RANK(E51,$E$46:$E$95) -> 36 | H51: =IF(G51<=10,"⭐ Top 10","") | T51: =IF(AND('Raw Data'!G51=$B$17,'Raw Data'!K51=$E$17,'Raw Data'!N51>=$B$18),SUMPRODUCT(('Raw Data'!$G$2:$G51=$B$17)*('Raw Data'!$K$2:$K51=$E$17)*('Raw Data'!$N$2:$N51>=$B$18)),"") | U51: =IF($C51="Premium",SUMPRODUCT(($C$46:$C51="Premium")*1),"")
A52: CUST007 | B52: David Martinez | C52: =INDEX('Raw Data'!$L$2:$L$251,MATCH(A52,'Raw Data'!$C$2:$C$251,0)) -> Basic | D52: =COUNTIFS('Raw Data'!$C$2:$C$251,A52) -> 6 | E52: =SUMIFS('Raw Data'!$N$2:$N$251,'Raw Data'!$C$2:$C$251,A52) -> 1809.84 | F52: =IFERROR(E52/D52,0) -> 301.64 | G52: =RANK(E52,$E$46:$E$95) -> 39 | H52: =IF(G52<=10,"⭐ Top 10","") | T52: =IF(AND('Raw Data'!G52=$B$17,'Raw Data'!K52=$E$17,'Raw Data'!N52>=$B$18),SUMPRODUCT(('Raw Data'!$G$2:$G52=$B$17)*('Raw Data'!$K$2:$K52=$E$17)*('Raw Data'!$N$2:$N52>=$B$18)),"") | U52: =IF($C52="Premium",SUMPRODUCT(($C$46:$C52="Premium")*1),"")
A53: CUST008 | B53: Jennifer Taylor | C53: =INDEX('Raw Data'!$L$2:$L$251,MATCH(A53,'Raw Data'!$C$2:$C$251,0)) -> Standard | D53: =COUNTIFS('Raw Data'!$C$2:$C$251,A53) -> 4 | E53: =SUMIFS('Raw Data'!$N$2:$N$251,'Raw Data'!$C$2:$C$251,A53) -> 4739.85 | F53: =IFERROR(E53/D53,0) -> 1184.9625 | G53: =RANK(E53,$E$46:$E$95) -> 24 | H53: =IF(G53<=10,"⭐ Top 10","") | T53: =IF(AND('Raw Data'!G53=$B$17,'Raw Data'!K53=$E$17,'Raw Data'!N53>=$B$18),SUMPRODUCT(('Raw Data'!$G$2:$G53=$B$17)*('Raw Data'!$K$2:$K53=$E$17)*('Raw Data'!$N$2:$N53>=$B$18)),"") | U53: =IF($C53="Premium",SUMPRODUCT(($C$46:$C53="Premium")*1),"")
A54: CUST009 | B54: Robert Thomas | C54: =INDEX('Raw Data'!$L$2:$L$251,MATCH(A54,'Raw Data'!$C$2:$C$251,0)) -> Standard | D54: =COUNTIFS('Raw Data'!$C$2:$C$251,A54) -> 5 | E54: =SUMIFS('Raw Data'!$N$2:$N$251,'Raw Data'!$C$2:$C$251,A54) -> 3509.9 | F54: =IFERROR(E54/D54,0) -> 701.98 | G54: =RANK(E54,$E$46:$E$95) -> 32 | H54: =IF(G54<=10,"⭐ Top 10","") | T54: =IF(AND('Raw Data'!G54=$B$17,'Raw Data'!K54=$E$17,'Raw Data'!N54>=$B$18),SUMPRODUCT(('Raw Data'!$G$2:$G54=$B$17)*('Raw Data'!$K$2:$K54=$E$17)*('Raw Data'!$N$2:$N54>=$B$18)),"") | U54: =IF($C54="Premium",SUMPRODUCT(($C$46:$C54="Premium")*1),"")
A55: CUST010 | B55: Maria Garcia | C55: =INDEX('Raw Data'!$L$2:$L$251,MATCH(A55,'Raw Data'!$C$2:$C$251,0)) -> Basic | D55: =COUNTIFS('Raw Data'!$C$2:$C$251,A55) -> 4 | E55: =SUMIFS('Raw Data'!$N$2:$N$251,'Raw Data'!$C$2:$C$251,A55) -> 1909.93 | F55: =IFERROR(E55/D55,0) -> 477.4825 | G55: =RANK(E55,$E$46:$E$95) -> 38 | H55: =IF(G55<=10,"⭐ Top 10","") | T55: =IF(AND('Raw Data'!G55=$B$17,'Raw Data'!K55=$E$17,'Raw Data'!N55>=$B$18),SUMPRODUCT(('Raw Data'!$G$2:$G55=$B$17)*('Raw Data'!$K$2:$K55=$E$17)*('Raw Data'!$N$2:$N55>=$B$18)),"") | U55: =IF($C55="Premium",SUMPRODUCT(($C$46:$C55="Premium")*1),"")
A56: CUST011 | B56: William White | C56: =INDEX('Raw Data'!$L$2:$L$251,MATCH(A56,'Raw Data'!$C$2:$C$251,0)) -> Standard | D56: =COUNTIFS('Raw Data'!$C$2:$C$251,A56) -> 3 | E56: =SUMIFS('Raw Data'!$N$2:$N$251,'Raw Data'!$C$2:$C$251,A56) -> 4749.91 | F56: =IFERROR(E56/D56,0) -> 1583.3033 | G56: =RANK(E56,$E$46:$E$95) -> 23 | H56: =IF(G56<=10,"⭐ Top 10","") | T56: =IF(AND('Raw Data'!G56=$B$17,'Raw Data'!K56=$E$17,'Raw Data'!N56>=$B$18),SUMPRODUCT(('Raw Data'!$G$2:$G56=$B$17)*('Raw Data'!$K$2:$K56=$E$17)*('Raw Data'!$N$2:$N56>=$B$18)),"") | U56: =IF($C56="Premium",SUMPRODUCT(($C$46:$C56="Premium")*1),"")
A57: CUST012 | B57: Patricia Moore | C57: =INDEX('Raw Data'!$L$2:$L$251,MATCH(A57,'Raw Data'!$C$2:$C$251,0)) -> Standard | D57: =COUNTIFS('Raw Data'!$C$2:$C$251,A57) -> 8 | E57: =SUMIFS('Raw Data'!$N$2:$N$251,'Raw Data'!$C$2:$C$251,A57) -> 9799.73 | F57: =IFERROR(E57/D57,0) -> 1224.9662 | G57: =RANK(E57,$E$46:$E$95) -> 4 | H57: =IF(G57<=10,"⭐ Top 10","") -> ⭐ Top 10 | T57: =IF(AND('Raw Data'!G57=$B$17,'Raw Data'!K57=$E$17,'Raw Data'!N57>=$B$18),SUMPRODUCT(('Raw Data'!$G$2:$G57=$B$17)*('Raw Data'!$K$2:$K57=$E$17)*('Raw Data'!$N$2:$N57>=$B$18)),"") | U57: =IF($C57="Premium",SUMPRODUCT(($C$46:$C57="Premium")*1),"")
... A95: CUST050 | B95: Julie Foster | C95: =INDEX('Raw Data'!$L$2:$L$251,MATCH(A95,'Raw Data'!$C$2:$C$251,0)) -> Standard | D95: =COUNTIFS('Raw Data'!$C$2:$C$251,A95) -> 1 | E95: =SUMIFS('Raw Data'!$N$2:$N$251,'Raw Data'!$C$2:$C$251,A95) -> 239.96 | F95: =IFERROR(E95/D95,0) -> 239.96 | G95: =RANK(E95,$E$46:$E$95) -> 49 | H95: =IF(G95<=10,"⭐ Top 10","") | T95: =IF(AND('Raw Data'!G95=$B$17,'Raw Data'!K95=$E$17,'Raw Data'!N95>=$B$18),SUMPRODUCT(('Raw Data'!$G$2:$G95=$B$17)*('Raw Data'!$K$2:$K95=$E$17)*('Raw Data'!$N$2:$N95>=$B$18)),"") | U95: =IF($C95="Premium",SUMPRODUCT(($C$46:$C95="Premium")*1),"")
T96: =IF(AND('Raw Data'!G96=$B$17,'Raw Data'!K96=$E$17,'Raw Data'!N96>=$B$18),SUMPRODUCT(('Raw Data'!$G$2:$G96=$B$17)*('Raw Data'!$K$2:$K96=$E$17)*('Raw Data'!$N$2:$N96>=$B$18)),"")
A97: D. Most Frequently Purchased Product & Repeat Customers | T97: =IF(AND('Raw Data'!G97=$B$17,'Raw Data'!K97=$E$17,'Raw Data'!N97>=$B$18),SUMPRODUCT(('Raw Data'!$G$2:$G97=$B$17)*('Raw Data'!$K$2:$K97=$E$17)*('Raw Data'!$N$2:$N97>=$B$18)),"")
A98: Product_ID | B98: Product_Name | C98: Category | D98: Times Purchased | E98: Units Sold | F98: Revenue | T98: =IF(AND('Raw Data'!G98=$B$17,'Raw Data'!K98=$E$17,'Raw Data'!N98>=$B$18),SUMPRODUCT(('Raw Data'!$G$2:$G98=$B$17)*('Raw Data'!$K$2:$K98=$E$17)*('Raw Data'!$N$2:$N98>=$B$18)),"")
A99: P001 | B99: Laptop | C99: Electronics | D99: =COUNTIF('Raw Data'!$E$2:$E$251,A99) -> 24 | E99: =SUMIF('Raw Data'!$E$2:$E$251,A99,'Raw Data'!$H$2:$H$251) -> 75 | F99: =SUMIF('Raw Data'!$E$2:$E$251,A99,'Raw Data'!$N$2:$N$251) -> 67499.25 | T99: =IF(AND('Raw Data'!G99=$B$17,'Raw Data'!K99=$E$17,'Raw Data'!N99>=$B$18),SUMPRODUCT(('Raw Data'!$G$2:$G99=$B$17)*('Raw Data'!$K$2:$K99=$E$17)*('Raw Data'!$N$2:$N99>=$B$18)),"")
A100: P002 | B100: Smartphone | C100: Electronics | D100: =COUNTIF('Raw Data'!$E$2:$E$251,A100) -> 31 | E100: =SUMIF('Raw Data'!$E$2:$E$251,A100,'Raw Data'!$H$2:$H$251) -> 96 | F100: =SUMIF('Raw Data'!$E$2:$E$251,A100,'Raw Data'!$N$2:$N$251) -> 67199.04 | T100: =IF(AND('Raw Data'!G100=$B$17,'Raw Data'!K100=$E$17,'Raw Data'!N100>=$B$18),SUMPRODUCT(('Raw Data'!$G$2:$G100=$B$17)*('Raw Data'!$K$2:$K100=$E$17)*('Raw Data'!$N$2:$N100>=$B$18)),"")
A101: P003 | B101: Headphones | C101: Electronics | D101: =COUNTIF('Raw Data'!$E$2:$E$251,A101) -> 16 | E101: =SUMIF('Raw Data'!$E$2:$E$251,A101,'Raw Data'!$H$2:$H$251) -> 47 | F101: =SUMIF('Raw Data'!$E$2:$E$251,A101,'Raw Data'!$N$2:$N$251) -> 7049.53 | T101: =IF(AND('Raw Data'!G101=$B$17,'Raw Data'!K101=$E$17,'Raw Data'!N101>=$B$18),SUMPRODUCT(('Raw Data'!$G$2:$G101=$B$17)*('Raw Data'!$K$2:$K101=$E$17)*('Raw Data'!$N$2:$N101>=$B$18)),"")
A102: P004 | B102: Coffee Maker | C102: Appliances | D102: =COUNTIF('Raw Data'!$E$2:$E$251,A102) -> 14 | E102: =SUMIF('Raw Data'!$E$2:$E$251,A102,'Raw Data'!$H$2:$H$251) -> 39 | F102: =SUMIF('Raw Data'!$E$2:$E$251,A102,'Raw Data'!$N$2:$N$251) -> 3119.61 | T102: =IF(AND('Raw Data'!G102=$B$17,'Raw Data'!K102=$E$17,'Raw Data'!N102>=$B$18),SUMPRODUCT(('Raw Data'!$G$2:$G102=$B$17)*('Raw Data'!$K$2:$K102=$E$17)*('Raw Data'!$N$2:$N102>=$B$18)),"") -> 7
A103: P005 | B103: Blender | C103: Appliances | D103: =COUNTIF('Raw Data'!$E$2:$E$251,A103) -> 29 | E103: =SUMIF('Raw Data'!$E$2:$E$251,A103,'Raw Data'!$H$2:$H$251) -> 87 | F103: =SUMIF('Raw Data'!$E$2:$E$251,A103,'Raw Data'!$N$2:$N$251) -> 5219.13 | T103: =IF(AND('Raw Data'!G103=$B$17,'Raw Data'!K103=$E$17,'Raw Data'!N103>=$B$18),SUMPRODUCT(('Raw Data'!$G$2:$G103=$B$17)*('Raw Data'!$K$2:$K103=$E$17)*('Raw Data'!$N$2:$N103>=$B$18)),"")
A104: P006 | B104: Office Chair | C104: Furniture | D104: =COUNTIF('Raw Data'!$E$2:$E$251,A104) -> 15 | E104: =SUMIF('Raw Data'!$E$2:$E$251,A104,'Raw Data'!$H$2:$H$251) -> 52 | F104: =SUMIF('Raw Data'!$E$2:$E$251,A104,'Raw Data'!$N$2:$N$251) -> 10399.48 | T104: =IF(AND('Raw Data'!G104=$B$17,'Raw Data'!K104=$E$17,'Raw Data'!N104>=$B$18),SUMPRODUCT(('Raw Data'!$G$2:$G104=$B$17)*('Raw Data'!$K$2:$K104=$E$17)*('Raw Data'!$N$2:$N104>=$B$18)),"")
A105: P007 | B105: Desk | C105: Furniture | D105: =COUNTIF('Raw Data'!$E$2:$E$251,A105) -> 26 | E105: =SUMIF('Raw Data'!$E$2:$E$251,A105,'Raw Data'!$H$2:$H$251) -> 78 | F105: =SUMIF('Raw Data'!$E$2:$E$251,A105,'Raw Data'!$N$2:$N$251) -> 23399.22 | T105: =IF(AND('Raw Data'!G105=$B$17,'Raw Data'!K105=$E$17,'Raw Data'!N105>=$B$18),SUMPRODUCT(('Raw Data'!$G$2:$G105=$B$17)*('Raw Data'!$K$2:$K105=$E$17)*('Raw Data'!$N$2:$N105>=$B$18)),"")
A106: P008 | B106: Bookshelf | C106: Furniture | D106: =COUNTIF('Raw Data'!$E$2:$E$251,A106) -> 35 | E106: =SUMIF('Raw Data'!$E$2:$E$251,A106,'Raw Data'!$H$2:$H$251) -> 102 | F106: =SUMIF('Raw Data'!$E$2:$E$251,A106,'Raw Data'!$N$2:$N$251) -> 15298.98 | T106: =IF(AND('Raw Data'!G106=$B$17,'Raw Data'!K106=$E$17,'Raw Data'!N106>=$B$18),SUMPRODUCT(('Raw Data'!$G$2:$G106=$B$17)*('Raw Data'!$K$2:$K106=$E$17)*('Raw Data'!$N$2:$N106>=$B$18)),"")
A107: P009 | B107: Monitor | C107: Electronics | D107: =COUNTIF('Raw Data'!$E$2:$E$251,A107) -> 26 | E107: =SUMIF('Raw Data'!$E$2:$E$251,A107,'Raw Data'!$H$2:$H$251) -> 88 | F107: =SUMIF('Raw Data'!$E$2:$E$251,A107,'Raw Data'!$N$2:$N$251) -> 21999.12 | T107: =IF(AND('Raw Data'!G107=$B$17,'Raw Data'!K107=$E$17,'Raw Data'!N107>=$B$18),SUMPRODUCT(('Raw Data'!$G$2:$G107=$B$17)*('Raw Data'!$K$2:$K107=$E$17)*('Raw Data'!$N$2:$N107>=$B$18)),"")
A108: P010 | B108: Keyboard | C108: Electronics | D108: =COUNTIF('Raw Data'!$E$2:$E$251,A108) -> 34 | E108: =SUMIF('Raw Data'!$E$2:$E$251,A108,'Raw Data'!$H$2:$H$251) -> 89 | F108: =SUMIF('Raw Data'!$E$2:$E$251,A108,'Raw Data'!$N$2:$N$251) -> 8009.11 | T108: =IF(AND('Raw Data'!G108=$B$17,'Raw Data'!K108=$E$17,'Raw Data'!N108>=$B$18),SUMPRODUCT(('Raw Data'!$G$2:$G108=$B$17)*('Raw Data'!$K$2:$K108=$E$17)*('Raw Data'!$N$2:$N108>=$B$18)),"")
T109: =IF(AND('Raw Data'!G109=$B$17,'Raw Data'!K109=$E$17,'Raw Data'!N109>=$B$18),SUMPRODUCT(('Raw Data'!$G$2:$G109=$B$17)*('Raw Data'!$K$2:$K109=$E$17)*('Raw Data'!$N$2:$N109>=$B$18)),"")
A110: Most Frequently Purchased Product: | C110: =INDEX($B$99:$B$108,MATCH(MAX($D$99:$D$108),$D$99:$D$108,0)) -> Bookshelf | T110: =IF(AND('Raw Data'!G110=$B$17,'Raw Data'!K110=$E$17,'Raw Data'!N110>=$B$18),SUMPRODUCT(('Raw Data'!$G$2:$G110=$B$17)*('Raw Data'!$K$2:$K110=$E$17)*('Raw Data'!$N$2:$N110>=$B$18)),"")
A111: Highest-Revenue Product: | C111: =INDEX($B$99:$B$108,MATCH(MAX($F$99:$F$108),$F$99:$F$108,0)) -> Laptop | T111: =IF(AND('Raw Data'!G111=$B$17,'Raw Data'!K111=$E$17,'Raw Data'!N111>=$B$18),SUMPRODUCT(('Raw Data'!$G$2:$G111=$B$17)*('Raw Data'!$K$2:$K111=$E$17)*('Raw Data'!$N$2:$N111>=$B$18)),"")
A112: Most Frequent Repeat Customer (by # transactions): | C112: =INDEX(Analysis!$B$46:$B$95,MATCH(MAX(Analysis!$D$46:$D$95),Analysis!$D$46:$D$95,0)) -> Mark Carter | T112: =IF(AND('Raw Data'!G112=$B$17,'Raw Data'!K112=$E$17,'Raw Data'!N112>=$B$18),SUMPRODUCT(('Raw Data'!$G$2:$G112=$B$17)*('Raw Data'!$K$2:$K112=$E$17)*('Raw Data'!$N$2:$N112>=$B$18)),"") -> 8
A113: → that customer's transaction count: | C113: =MAX(Analysis!$D$46:$D$95) -> 12 | T113: =IF(AND('Raw Data'!G113=$B$17,'Raw Data'!K113=$E$17,'Raw Data'!N113>=$B$18),SUMPRODUCT(('Raw Data'!$G$2:$G113=$B$17)*('Raw Data'!$K$2:$K113=$E$17)*('Raw Data'!$N$2:$N113>=$B$18)),"")
T114: =IF(AND('Raw Data'!G114=$B$17,'Raw Data'!K114=$E$17,'Raw Data'!N114>=$B$18),SUMPRODUCT(('Raw Data'!$G$2:$G114=$B$17)*('Raw Data'!$K$2:$K114=$E$17)*('Raw Data'!$N$2:$N114>=$B$18)),"")
A115: E. Compare Two Lists — Customers who are BOTH 'Top 10 by Spend' AND 'Premium Segment' | T115: =IF(AND('Raw Data'!G115=$B$17,'Raw Data'!K115=$E$17,'Raw Data'!N115>=$B$18),SUMPRODUCT(('Raw Data'!$G$2:$G115=$B$17)*('Raw Data'!$K$2:$K115=$E$17)*('Raw Data'!$N$2:$N115>=$B$18)),"")
A116: List 1: Top 10 by Spend | C116: List 2: Premium Segment | E116: In Both Lists (Match) | T116: =IF(AND('Raw Data'!G116=$B$17,'Raw Data'!K116=$E$17,'Raw Data'!N116>=$B$18),SUMPRODUCT(('Raw Data'!$G$2:$G116=$B$17)*('Raw Data'!$K$2:$K116=$E$17)*('Raw Data'!$N$2:$N116>=$B$18)),"")
A117: =IFERROR(INDEX($B$46:$B$95,MATCH(1,$G$46:$G$95,0)),"") -> Mark Carter | C117: =IFERROR(INDEX($B$46:$B$95,MATCH(1,$U$46:$U$95,0)),"") -> Emma Wilson | E117: =IF(A117="","",IF(COUNTIF($C$117:$C$136,A117)>0,"✔ Match","—")) -> ✔ Match | T117: =IF(AND('Raw Data'!G117=$B$17,'Raw Data'!K117=$E$17,'Raw Data'!N117>=$B$18),SUMPRODUCT(('Raw Data'!$G$2:$G117=$B$17)*('Raw Data'!$K$2:$K117=$E$17)*('Raw Data'!$N$2:$N117>=$B$18)),"")
A118: =IFERROR(INDEX($B$46:$B$95,MATCH(2,$G$46:$G$95,0)),"") -> Edward Mitchell | C118: =IFERROR(INDEX($B$46:$B$95,MATCH(2,$U$46:$U$95,0)),"") -> Michael Brown | E118: =IF(A118="","",IF(COUNTIF($C$117:$C$136,A118)>0,"✔ Match","—")) -> — | T118: =IF(AND('Raw Data'!G118=$B$17,'Raw Data'!K118=$E$17,'Raw Data'!N118>=$B$18),SUMPRODUCT(('Raw Data'!$G$2:$G118=$B$17)*('Raw Data'!$K$2:$K118=$E$17)*('Raw Data'!$N$2:$N118>=$B$18)),"") -> 9
A119: =IFERROR(INDEX($B$46:$B$95,MATCH(3,$G$46:$G$95,0)),"") -> Barbara Young | C119: =IFERROR(INDEX($B$46:$B$95,MATCH(3,$U$46:$U$95,0)),"") -> James Johnson | E119: =IF(A119="","",IF(COUNTIF($C$117:$C$136,A119)>0,"✔ Match","—")) -> — | T119: =IF(AND('Raw Data'!G119=$B$17,'Raw Data'!K119=$E$17,'Raw Data'!N119>=$B$18),SUMPRODUCT(('Raw Data'!$G$2:$G119=$B$17)*('Raw Data'!$K$2:$K119=$E$17)*('Raw Data'!$N$2:$N119>=$B$18)),"")
A120: =IFERROR(INDEX($B$46:$B$95,MATCH(4,$G$46:$G$95,0)),"") -> Patricia Moore | C120: =IFERROR(INDEX($B$46:$B$95,MATCH(4,$U$46:$U$95,0)),"") -> Joseph Jackson | E120: =IF(A120="","",IF(COUNTIF($C$117:$C$136,A120)>0,"✔ Match","—")) -> — | T120: =IF(AND('Raw Data'!G120=$B$17,'Raw Data'!K120=$E$17,'Raw Data'!N120>=$B$18),SUMPRODUCT(('Raw Data'!$G$2:$G120=$B$17)*('Raw Data'!$K$2:$K120=$E$17)*('Raw Data'!$N$2:$N120>=$B$18)),"")
A121: =IFERROR(INDEX($B$46:$B$95,MATCH(5,$G$46:$G$95,0)),"") -> Paul Baker | C121: =IFERROR(INDEX($B$46:$B$95,MATCH(5,$U$46:$U$95,0)),"") -> Linda Martin | E121: =IF(A121="","",IF(COUNTIF($C$117:$C$136,A121)>0,"✔ Match","—")) -> — | T121: =IF(AND('Raw Data'!G121=$B$17,'Raw Data'!K121=$E$17,'Raw Data'!N121>=$B$18),SUMPRODUCT(('Raw Data'!$G$2:$G121=$B$17)*('Raw Data'!$K$2:$K121=$E$17)*('Raw Data'!$N$2:$N121>=$B$18)),"")
A122: =IFERROR(INDEX($B$46:$B$95,MATCH(6,$G$46:$G$95,0)),"") -> Dorothy Nelson | C122: =IFERROR(INDEX($B$46:$B$95,MATCH(6,$U$46:$U$95,0)),"") -> Mark Carter | E122: =IF(A122="","",IF(COUNTIF($C$117:$C$136,A122)>0,"✔ Match","—")) -> — | T122: =IF(AND('Raw Data'!G122=$B$17,'Raw Data'!K122=$E$17,'Raw Data'!N122>=$B$18),SUMPRODUCT(('Raw Data'!$G$2:$G122=$B$17)*('Raw Data'!$K$2:$K122=$E$17)*('Raw Data'!$N$2:$N122>=$B$18)),"")
A123: =IFERROR(INDEX($B$46:$B$95,MATCH(7,$G$46:$G$95,0)),"") -> Karen Hill | C123: =IFERROR(INDEX($B$46:$B$95,MATCH(7,$U$46:$U$95,0)),"") -> Karen Hill | E123: =IF(A123="","",IF(COUNTIF($C$117:$C$136,A123)>0,"✔ Match","—")) -> ✔ Match | T123: =IF(AND('Raw Data'!G123=$B$17,'Raw Data'!K123=$E$17,'Raw Data'!N123>=$B$18),SUMPRODUCT(('Raw Data'!$G$2:$G123=$B$17)*('Raw Data'!$K$2:$K123=$E$17)*('Raw Data'!$N$2:$N123>=$B$18)),"")
A124: =IFERROR(INDEX($B$46:$B$95,MATCH(8,$G$46:$G$95,0)),"") -> Daniel King | C124: =IFERROR(INDEX($B$46:$B$95,MATCH(8,$U$46:$U$95,0)),"") -> Steven Turner | E124: =IF(A124="","",IF(COUNTIF($C$117:$C$136,A124)>0,"✔ Match","—")) -> — | T124: =IF(AND('Raw Data'!G124=$B$17,'Raw Data'!K124=$E$17,'Raw Data'!N124>=$B$18),SUMPRODUCT(('Raw Data'!$G$2:$G124=$B$17)*('Raw Data'!$K$2:$K124=$E$17)*('Raw Data'!$N$2:$N124>=$B$18)),"") -> 10
A125: =IFERROR(INDEX($B$46:$B$95,MATCH(9,$G$46:$G$95,0)),"") -> Lawrence Reed | C125: =IFERROR(INDEX($B$46:$B$95,MATCH(9,$U$46:$U$95,0)),"") -> Sandra Phillips | E125: =IF(A125="","",IF(COUNTIF($C$117:$C$136,A125)>0,"✔ Match","—")) -> ✔ Match | T125: =IF(AND('Raw Data'!G125=$B$17,'Raw Data'!K125=$E$17,'Raw Data'!N125>=$B$18),SUMPRODUCT(('Raw Data'!$G$2:$G125=$B$17)*('Raw Data'!$K$2:$K125=$E$17)*('Raw Data'!$N$2:$N125>=$B$18)),"")
A126: =IFERROR(INDEX($B$46:$B$95,MATCH(10,$G$46:$G$95,0)),"") -> Joseph Jackson | C126: =IFERROR(INDEX($B$46:$B$95,MATCH(10,$U$46:$U$95,0)),"") -> Frank Torres | E126: =IF(A126="","",IF(COUNTIF($C$117:$C$136,A126)>0,"✔ Match","—")) -> ✔ Match | T126: =IF(AND('Raw Data'!G126=$B$17,'Raw Data'!K126=$E$17,'Raw Data'!N126>=$B$18),SUMPRODUCT(('Raw Data'!$G$2:$G126=$B$17)*('Raw Data'!$K$2:$K126=$E$17)*('Raw Data'!$N$2:$N126>=$B$18)),"")
C127: =IFERROR(INDEX($B$46:$B$95,MATCH(11,$U$46:$U$95,0)),"") -> Carol Evans | T127: =IF(AND('Raw Data'!G127=$B$17,'Raw Data'!K127=$E$17,'Raw Data'!N127>=$B$18),SUMPRODUCT(('Raw Data'!$G$2:$G127=$B$17)*('Raw Data'!$K$2:$K127=$E$17)*('Raw Data'!$N$2:$N127>=$B$18)),"")
C128: =IFERROR(INDEX($B$46:$B$95,MATCH(12,$U$46:$U$95,0)),"") -> Harry Morgan | T128: =IF(AND('Raw Data'!G128=$B$17,'Raw Data'!K128=$E$17,'Raw Data'!N128>=$B$18),SUMPRODUCT(('Raw Data'!$G$2:$G128=$B$17)*('Raw Data'!$K$2:$K128=$E$17)*('Raw Data'!$N$2:$N128>=$B$18)),"")
C129: =IFERROR(INDEX($B$46:$B$95,MATCH(13,$U$46:$U$95,0)),"") -> Lawrence Reed | T129: =IF(AND('Raw Data'!G129=$B$17,'Raw Data'!K129=$E$17,'Raw Data'!N129>=$B$18),SUMPRODUCT(('Raw Data'!$G$2:$G129=$B$17)*('Raw Data'!$K$2:$K129=$E$17)*('Raw Data'!$N$2:$N129>=$B$18)),"")
C130: =IFERROR(INDEX($B$46:$B$95,MATCH(14,$U$46:$U$95,0)),"") -> Peter Richardson | T130: =IF(AND('Raw Data'!G130=$B$17,'Raw Data'!K130=$E$17,'Raw Data'!N130>=$B$18),SUMPRODUCT(('Raw Data'!$G$2:$G130=$B$17)*('Raw Data'!$K$2:$K130=$E$17)*('Raw Data'!$N$2:$N130>=$B$18)),"")
C131: =IFERROR(INDEX($B$46:$B$95,MATCH(15,$U$46:$U$95,0)),"") -> Kathleen Bennett | T131: =IF(AND('Raw Data'!G131=$B$17,'Raw Data'!K131=$E$17,'Raw Data'!N131>=$B$18),SUMPRODUCT(('Raw Data'!$G$2:$G131=$B$17)*('Raw Data'!$K$2:$K131=$E$17)*('Raw Data'!$N$2:$N131>=$B$18)),"")
C132: =IFERROR(INDEX($B$46:$B$95,MATCH(16,$U$46:$U$95,0)),"") -> Virginia Sanders | T132: =IF(AND('Raw Data'!G132=$B$17,'Raw Data'!K132=$E$17,'Raw Data'!N132>=$B$18),SUMPRODUCT(('Raw Data'!$G$2:$G132=$B$17)*('Raw Data'!$K$2:$K132=$E$17)*('Raw Data'!$N$2:$N132>=$B$18)),"")
C133: =IFERROR(INDEX($B$46:$B$95,MATCH(17,$U$46:$U$95,0)),"") | T133: =IF(AND('Raw Data'!G133=$B$17,'Raw Data'!K133=$E$17,'Raw Data'!N133>=$B$18),SUMPRODUCT(('Raw Data'!$G$2:$G133=$B$17)*('Raw Data'!$K$2:$K133=$E$17)*('Raw Data'!$N$2:$N133>=$B$18)),"")
C134: =IFERROR(INDEX($B$46:$B$95,MATCH(18,$U$46:$U$95,0)),"") | T134: =IF(AND('Raw Data'!G134=$B$17,'Raw Data'!K134=$E$17,'Raw Data'!N134>=$B$18),SUMPRODUCT(('Raw Data'!$G$2:$G134=$B$17)*('Raw Data'!$K$2:$K134=$E$17)*('Raw Data'!$N$2:$N134>=$B$18)),"")
C135: =IFERROR(INDEX($B$46:$B$95,MATCH(19,$U$46:$U$95,0)),"") | T135: =IF(AND('Raw Data'!G135=$B$17,'Raw Data'!K135=$E$17,'Raw Data'!N135>=$B$18),SUMPRODUCT(('Raw Data'!$G$2:$G135=$B$17)*('Raw Data'!$K$2:$K135=$E$17)*('Raw Data'!$N$2:$N135>=$B$18)),"")
C136: =IFERROR(INDEX($B$46:$B$95,MATCH(20,$U$46:$U$95,0)),"") | T136: =IF(AND('Raw Data'!G136=$B$17,'Raw Data'!K136=$E$17,'Raw Data'!N136>=$B$18),SUMPRODUCT(('Raw Data'!$G$2:$G136=$B$17)*('Raw Data'!$K$2:$K136=$E$17)*('Raw Data'!$N$2:$N136>=$B$18)),"") -> 11
T137: =IF(AND('Raw Data'!G137=$B$17,'Raw Data'!K137=$E$17,'Raw Data'!N137>=$B$18),SUMPRODUCT(('Raw Data'!$G$2:$G137=$B$17)*('Raw Data'!$K$2:$K137=$E$17)*('Raw Data'!$N$2:$N137>=$B$18)),"")
A138: Match logic: COUNTIF(List2, List1 value) > 0 — classic two-list comparison without VLOOKUP. | T138: =IF(AND('Raw Data'!G138=$B$17,'Raw Data'!K138=$E$17,'Raw Data'!N138>=$B$18),SUMPRODUCT(('Raw Data'!$G$2:$G138=$B$17)*('Raw Data'!$K$2:$K138=$E$17)*('Raw Data'!$N$2:$N138>=$B$18)),"")
T139: =IF(AND('Raw Data'!G139=$B$17,'Raw Data'!K139=$E$17,'Raw Data'!N139>=$B$18),SUMPRODUCT(('Raw Data'!$G$2:$G139=$B$17)*('Raw Data'!$K$2:$K139=$E$17)*('Raw Data'!$N$2:$N139>=$B$18)),"")
A140: F. Abbreviations Built with TEXT Functions (sample of first 15 transactions) | T140: =IF(AND('Raw Data'!G140=$B$17,'Raw Data'!K140=$E$17,'Raw Data'!N140>=$B$18),SUMPRODUCT(('Raw Data'!$G$2:$G140=$B$17)*('Raw Data'!$K$2:$K140=$E$17)*('Raw Data'!$N$2:$N140>=$B$18)),"")
A141: Transaction_ID | B141: Customer_Name | C141: Customer_Initials | D141: Region | E141: Region_Code | F141: Product_Name | G141: Product_Code | H141: Short_Label | T141: =IF(AND('Raw Data'!G141=$B$17,'Raw Data'!K141=$E$17,'Raw Data'!N141>=$B$18),SUMPRODUCT(('Raw Data'!$G$2:$G141=$B$17)*('Raw Data'!$K$2:$K141=$E$17)*('Raw Data'!$N$2:$N141>=$B$18)),"")
A142: ='Raw Data'!A2 -> TRX0155 | B142: ='Raw Data'!D2 -> Paul Baker | C142: =UPPER(LEFT(B142,1))&UPPER(LEFT(MID(B142,FIND(" ",B142)+1,50),1)) -> PB | D142: ='Raw Data'!K2 -> Central | E142: =UPPER(LEFT(D142,3)) -> CEN | F142: ='Raw Data'!F2 -> Monitor | G142: =UPPER(LEFT(SUBSTITUTE(F142," ",""),4)) -> MONI | H142: ="TXN-"&TEXT(ROW()-142+1,"000")&"-"&E142&"-"&G142&"-"&C142 -> TXN-001-CEN-MONI-PB | T142: =IF(AND('Raw Data'!G142=$B$17,'Raw Data'!K142=$E$17,'Raw Data'!N142>=$B$18),SUMPRODUCT(('Raw Data'!$G$2:$G142=$B$17)*('Raw Data'!$K$2:$K142=$E$17)*('Raw Data'!$N$2:$N142>=$B$18)),"")
A143: ='Raw Data'!A3 -> TRX0023 | B143: ='Raw Data'!D3 -> Joseph Jackson | C143: =UPPER(LEFT(B143,1))&UPPER(LEFT(MID(B143,FIND(" ",B143)+1,50),1)) -> JJ | D143: ='Raw Data'!K3 -> Central | E143: =UPPER(LEFT(D143,3)) -> CEN | F143: ='Raw Data'!F3 -> Monitor | G143: =UPPER(LEFT(SUBSTITUTE(F143," ",""),4)) -> MONI | H143: ="TXN-"&TEXT(ROW()-142+1,"000")&"-"&E143&"-"&G143&"-"&C143 -> TXN-002-CEN-MONI-JJ | T143: =IF(AND('Raw Data'!G143=$B$17,'Raw Data'!K143=$E$17,'Raw Data'!N143>=$B$18),SUMPRODUCT(('Raw Data'!$G$2:$G143=$B$17)*('Raw Data'!$K$2:$K143=$E$17)*('Raw Data'!$N$2:$N143>=$B$18)),"")
A144: ='Raw Data'!A4 -> TRX0139 | B144: ='Raw Data'!D4 -> Kevin Scott | C144: =UPPER(LEFT(B144,1))&UPPER(LEFT(MID(B144,FIND(" ",B144)+1,50),1)) -> KS | D144: ='Raw Data'!K4 -> South | E144: =UPPER(LEFT(D144,3)) -> SOU | F144: ='Raw Data'!F4 -> Blender | G144: =UPPER(LEFT(SUBSTITUTE(F144," ",""),4)) -> BLEN | H144: ="TXN-"&TEXT(ROW()-142+1,"000")&"-"&E144&"-"&G144&"-"&C144 -> TXN-003-SOU-BLEN-KS | T144: =IF(AND('Raw Data'!G144=$B$17,'Raw Data'!K144=$E$17,'Raw Data'!N144>=$B$18),SUMPRODUCT(('Raw Data'!$G$2:$G144=$B$17)*('Raw Data'!$K$2:$K144=$E$17)*('Raw Data'!$N$2:$N144>=$B$18)),"")
...

Sheet Visualizations
A1: Visualizations — Pivot-style Charts & PivotTable Setup Guide
A3: Revenue by Payment Method | D3: Revenue by Customer Segment
A4: Payment_Method | B4: Revenue | D4: Segment | E4: Revenue
A5: Cash | B5: =SUMIF('Raw Data'!$J$2:$J$251,A5,'Raw Data'!$N$2:$N$251) -> 57427.79 | D5: Basic | E5: =SUMIF('Raw Data'!$L$2:$L$251,D5,'Raw Data'!$N$2:$N$251) -> 62177.81
A6: Credit Card | B6: =SUMIF('Raw Data'!$J$2:$J$251,A6,'Raw Data'!$N$2:$N$251) -> 61447.96 | D6: Standard | E6: =SUMIF('Raw Data'!$L$2:$L$251,D6,'Raw Data'!$N$2:$N$251) -> 82357.54
A7: Debit Card | B7: =SUMIF('Raw Data'!$J$2:$J$251,A7,'Raw Data'!$N$2:$N$251) -> 52118.31 | D7: Premium | E7: =SUMIF('Raw Data'!$L$2:$L$251,D7,'Raw Data'!$N$2:$N$251) -> 84657.12
A8: PayPal | B8: =SUMIF('Raw Data'!$J$2:$J$251,A8,'Raw Data'!$N$2:$N$251) -> 58198.41
A11: Product Revenue (all 10 products, sorted by ID)
A12: Product | B12: Revenue
A13: =Analysis!B99 -> Laptop | B13: =Analysis!F99 -> 67499.25
A14: =Analysis!B100 -> Smartphone | B14: =Analysis!F100 -> 67199.04
A15: =Analysis!B101 -> Headphones | B15: =Analysis!F101 -> 7049.53
A16: =Analysis!B102 -> Coffee Maker | B16: =Analysis!F102 -> 3119.61
A17: =Analysis!B103 -> Blender | B17: =Analysis!F103 -> 5219.13
A18: =Analysis!B104 -> Office Chair | B18: =Analysis!F104 -> 10399.48
A19: =Analysis!B105 -> Desk | B19: =Analysis!F105 -> 23399.22
A20: =Analysis!B106 -> Bookshelf | B20: =Analysis!F106 -> 15298.98
A21: =Analysis!B107 -> Monitor | B21: =Analysis!F107 -> 21999.12
A22: =Analysis!B108 -> Keyboard | B22: =Analysis!F108 -> 8009.11
A58: Build a Native Excel PivotTable + Slicers + Timeline (manual, one-time setup)
A59: 1. Click any cell inside the 'RawData' table on the 'Raw Data' sheet.
A60: 2. Insert → PivotTable → New Worksheet. Excel auto-detects the RawData table as the source.
A61: 3. Drag 'Region' or 'Category' to Rows, 'Total_Amount' to Values (Sum), 'Product_Name' to Columns for a cross-tab.
A62: 4. PivotTable Analyze tab → Insert Slicer → tick Region, Category, Customer_Segment, Payment_Method.
A63: 5. PivotTable Analyze tab → Insert Timeline → tick Date — gives a drag-to-filter month/quarter/year control.
A64: 6. Insert → PivotChart (or select the PivotTable → Insert → Recommended Charts) for a chart that filters live with the slicers/timeline.
A65: 7. Arrange the Slicers, Timeline, and PivotChart together on a new 'Live Dashboard' tab for a fully interactive slicer-driven view.
A67: Why manual: real Excel PivotTables/Slicers/Timelines are stored as live cache + UI objects that only Excel's own engine can (re)build safely; the summary tables and charts above already give you the same insights and refresh automatically from formulas, no PivotTable required.

Sheet Dashboard
A1: Customer Transactions — Data Intelligence Dashboard
A2: ="Last refreshed: "&TEXT(Analysis!B4,"mmm dd, yyyy hh:mm AM/PM") -> Last refreshed: Sep 23, 2026 11:22 AM
A4: Total Revenue | C4: Total Transactions | E4: Unique Customers | G4: Avg Order Value | I4: Total Units Sold | K4: Top Region
A5: =SUM('Raw Data'!N2:N251) -> 229192.47 | C5: =COUNTA('Raw Data'!A2:A251) -> 250 | E5: =SUMPRODUCT((COUNTIF('Raw Data'!C2:C251,'Raw Data'!C2:C251))^-1) -> 50 | G5: =AVERAGE('Raw Data'!N2:N251) -> 916.76988 | I5: =SUM('Raw Data'!H2:H251) -> 753 | K5: =INDEX({"Central";"East";"North";"South";"West"},MATCH(MAX(SUMIF('Raw Data'!K2:K251,{"Central";"East";"North";"South";"West"},'Raw Data'!N2:N251)),SUMIF('Raw Data'!K2:K251,{"Central";"East";"North";"South";"West"},'Raw Data'!N2:N251),0)) -> East
A8: Interactive Filter Panel (Slicer-style) — pick Region / Category / Month to update the KPIs below
A9: Region: | B9: All | D9: Category: | E9: All | G9: Segment: | H9: All
A10: Filtered Revenue: | B10: =SUMPRODUCT((($B$9="All")+('Raw Data'!$K$2:$K$251=$B$9))>0,((($E$9="All")+('Raw Data'!$G$2:$G$251=$E$9))>0)*1,((($H$9="All")+('Raw Data'!$L$2:$L$251=$H$9))>0)*1,'Raw Data'!$N$2:$N$251) -> 0 | D10: Filtered Transactions: | E10: =SUMPRODUCT((($B$9="All")+('Raw Data'!$K$2:$K$251=$B$9))>0,((($E$9="All")+('Raw Data'!$G$2:$G$251=$E$9))>0)*1,((($H$9="All")+('Raw Data'!$L$2:$L$251=$H$9))>0)*1) -> 0
A13: Revenue by Region (Pivot-style Summary) | E13: Revenue Share by Category
A14: Region | B14: Revenue | C14: Transactions | E14: Category | F14: Revenue
A15: Central | B15: =SUMIF('Raw Data'!$K$2:$K$251,A15,'Raw Data'!$N$2:$N$251) -> 41288.34 | C15: =COUNTIF('Raw Data'!$K$2:$K$251,A15) -> 54 | E15: Electronics | F15: =SUMIF('Raw Data'!$G$2:$G$251,E15,'Raw Data'!$N$2:$N$251) -> 171756.05
A16: East | B16: =SUMIF('Raw Data'!$K$2:$K$251,A16,'Raw Data'!$N$2:$N$251) -> 59288.39 | C16: =COUNTIF('Raw Data'!$K$2:$K$251,A16) -> 48 | E16: Appliances | F16: =SUMIF('Raw Data'!$G$2:$G$251,E16,'Raw Data'!$N$2:$N$251) -> 8338.74
A17: North | B17: =SUMIF('Raw Data'!$K$2:$K$251,A17,'Raw Data'!$N$2:$N$251) -> 50808.31 | C17: =COUNTIF('Raw Data'!$K$2:$K$251,A17) -> 59 | E17: Furniture | F17: =SUMIF('Raw Data'!$G$2:$G$251,E17,'Raw Data'!$N$2:$N$251) -> 49097.68
A18: South | B18: =SUMIF('Raw Data'!$K$2:$K$251,A18,'Raw Data'!$N$2:$N$251) -> 36398.75 | C18: =COUNTIF('Raw Data'!$K$2:$K$251,A18) -> 42
A19: West | B19: =SUMIF('Raw Data'!$K$2:$K$251,A19,'Raw Data'!$N$2:$N$251) -> 41408.68 | C19: =COUNTIF('Raw Data'!$K$2:$K$251,A19) -> 47
A22: Revenue Trend by Month | E22: KPI vs Target
A23: Month | B23: Revenue | D23: MoM Growth % | E23: KPI | F23: Actual | G23: Target | H23: % of Target
A24: =Analysis!A177 -> 45383 | B24: =Analysis!C177 -> 20919.33 | D24: 0 | E24: Total Revenue | F24: =B5 -> 0 | G24: 250000 | H24: =F24/G24 -> 0
A25: =Analysis!A178 -> 45413 | B25: =Analysis!C178 -> 17039.35 | D25: =IFERROR((B25-B24)/B24,0) -> -0.18547344 | E25: Avg Order Value | F25: =G5 -> 916.76988 | G25: 900 | H25: =F25/G25 -> 1.0186332
A26: =Analysis!A179 -> 45444 | B26: =Analysis!C179 -> 19299.45 | D26: =IFERROR((B26-B25)/B25,0) -> 0.13264004 | E26: Transactions | F26: =C5 -> 250 | G26: 260 | H26: =F26/G26 -> 0.96153846
A27: =Analysis!A180 -> 45474 | B27: =Analysis!C180 -> 18479.4 | D27: =IFERROR((B27-B26)/B26,0) -> -0.042490848
A28: =Analysis!A181 -> 45505 | B28: =Analysis!C181 -> 15759.43 | D28: =IFERROR((B28-B27)/B27,0) -> -0.1471893
A29: =Analysis!A182 -> 45536 | B29: =Analysis!C182 -> 12989.51 | D29: =IFERROR((B29-B28)/B28,0) -> -0.1757627
A30: =Analysis!A183 -> 45566 | B30: =Analysis!C183 -> 20609.52 | D30: =IFERROR((B30-B29)/B29,0) -> 0.58662798
A31: =Analysis!A184 -> 45597 | B31: =Analysis!C184 -> 12309.44 | D31: =IFERROR((B31-B30)/B30,0) -> -0.40273039
A32: =Analysis!A185 -> 45627 | B32: =Analysis!C185 -> 23039.3 | D32: =IFERROR((B32-B31)/B31,0) -> 0.87167735
A33: =Analysis!A186 -> 45658 | B33: =Analysis!C186 -> 25799.15 | D33: =IFERROR((B33-B32)/B32,0) -> 0.1197888
A34: =Analysis!A187 -> 45689 | B34: =Analysis!C187 -> 16069.38 | D34: =IFERROR((B34-B33)/B33,0) -> -0.37713529
A35: =Analysis!A188 -> 45717 | B35: =Analysis!C188 -> 19899.38 | D35: =IFERROR((B35-B34)/B34,0) -> 0.23834149
A36: =Analysis!A189 -> 45748 | B36: =Analysis!C189 -> 6979.83 | D36: =IFERROR((B36-B35)/B35,0) -> -0.64924385
A39: Target values above are illustrative planning benchmarks (documented here, not sourced externally) — replace with your actual targets. Charts and the real Excel PivotTable/Slicer/Timeline setup are on the 'Visualizations' sheet and the ReadMe tab.
