Workbook

Sheet Instructions
A1: RW Skill — Excel Interactive Dashboard Project
A4: Purpose | B4: This workbook completes the 6-task assignment shown in your task sheet, in order.
A5: Time Limit | B5: 3 hours (task sheet, Sr.No.1)
A6: Dataset | B6: Synthetic retail-sales dataset (see Documentation sheet for why, and what to change if a real Kaggle/UCI file is required)
A8: Sheet | B8: Maps to Task
A9: Raw_Data | B9: Task 1 — Dataset Selection & Import (as originally received, messy on purpose)
A10: Cleaned_Data | B10: Task 2 — Data Cleaning & Preparation (dedup, missing values handled, types formatted)
A11: Reference | B11: Lookup tables used by formulas (category margin %, region sales targets)
A12: Summary_Analysis | B12: Task 3 — Pivot-style summary tables (SUMIFS-based — see IMPORTANT note below)
A13: Formulas_Demo | B13: Task 4 — Advanced Formulas: VLOOKUP, INDEX-MATCH, nested IF, IFERROR
A14: Dashboard | B14: Task 5 & 6 — Charts, conditional formatting, KPI cards, region filter
A16: IMPORTANT | B16: openpyxl (the tool used to generate this file) cannot create native Excel PivotTable
B17: or Slicer objects. Summary_Analysis uses SUMIFS formulas to reproduce pivot-style output.
B18: Your task sheet explicitly asks for 'Create Pivot Tables' and 'Slicers, Timeline' — those are
B19: graded items you must add yourself in Excel. Exact steps are on the Documentation sheet.
B20: Do this BEFORE submitting, and be ready to explain it live in the viva.

Sheet Reference
A1: Reference — lookup tables used across the workbook
A3: Category | B3: Margin % | D3: Region | E3: Sales Target ($)
A4: Electronics | B4: 0.28 | D4: North | E4: 3000
A5: Furniture | B5: 0.18 | D5: South | E5: 3000
A6: Stationery | B6: 0.35 | D6: East | E6: 3000
A7: Apparel | B7: 0.22 | D7: West | E7: 3000
D8: Central | E8: 3000

Sheet Raw_Data
A1: Raw_Data — as imported (Task 1: contains duplicates & missing values on purpose)
A3: OrderID | B3: OrderDate | C3: CustomerID | D3: CustomerName | E3: Region | F3: Category | G3: Product | H3: Quantity | I3: UnitPrice | J3: Discount | K3: Sales | L3: Profit | M3: ShipMode
A4: 10297 | B4: 2024-07-29 | C4: CUST1146 | D4: Priya Gupta | E4: North | F4: Stationery | G4: Gel Pen Set | H4: 3 | I4: 4.25 | J4: 0.05 | K4: 12.11 | L4: 3.79 | M4: Priority
A5: 10362 | B5: 2024-02-19 | C5: CUST1061 | D5: Vihaan Singh | E5: North | F5: Furniture | G5: Study Desk | H5: 5 | I5: 120 | J5: 0 | K5: 600 | L5: 107.14 | M5: Express
A6: 10120 | B6: 2024-07-02 | C6: CUST1119 | D6: Aadhya Verma | E6: North | F6: Apparel | G6: Running Shoes | H6: 4 | I6: 55 | J6: 0 | K6: 220 | L6: 54.92 | M6: Priority
A7: 10340 | B7: 2024-07-14 | C7: CUST1039 | D7: Aadhya Patel | E7: West | F7: Furniture | G7: Bookshelf | H7: 4 | I7: 65 | J7: 0 | K7: 260 | L7: 43.64 | M7: Standard
A8: 10229 | B8: 2024-10-13 | C8: CUST1078 | D8: Reyansh Joshi | E8: West | F8: Stationery | G8: Notebook Pack | H8: 7 | I8: 5.5 | J8: 0.1 | K8: 34.65 | L8: 13.28 | M8: Standard
A9: 10007 | B9: 2024-04-29 | C9: CUST1006 | D9: Ananya Gupta | E9: North | F9: Apparel | G9: Running Shoes | H9: 8 | I9: 55 | J9: 0.15 | K9: 374 | L9: 73.95 | M9: Priority
A10: 10304 | B10: 2024-07-03 | C10: CUST1003 | D10: Rohan Gupta | E10: East | F10: Electronics | G10: USB-C Hub | H10: 3 | I10: 22 | J10: 0 | K10: 66 | L10: 17.91 | M10: Express
A11: 10179 | B11: 2024-08-12 | C11: CUST1028 | D11: Riya Sharma | F11: Furniture | G11: Office Chair | H11: 4 | I11: 89 | J11: 0.15 | K11: 302.6 | L11: 52.22 | M11: Priority
A12: 10148 | B12: 2024-11-17 | C12: CUST1147 | D12: Rohan Singh | E12: East | F12: Furniture | G12: Filing Cabinet | H12: 2 | I12: 75.5 | J12: 0.25 | K12: 113.25 | L12: 20.03 | M12: Priority
A13: 10224 | B13: 2024-03-22 | C13: CUST1073 | D13: Krishna Patel | E13: West | F13: Stationery | G13: Notebook Pack | H13: 5 | I13: 5.5 | J13: 0.15 | K13: 23.38 | L13: 8.46 | M13: Express
A14: 10077 | B14: 2024-10-28 | C14: CUST1076 | D14: Sai Singh | E14: Central | F14: Stationery | G14: Notebook Pack | H14: 4 | I14: 5.5 | J14: 0.1 | K14: 19.8 | L14: 6.36 | M14: Standard
A15: 10109 | B15: 2024-12-24 | C15: CUST1108 | D15: Vivaan Joshi | E15: East | F15: Electronics | G15: Laptop Stand | H15: 5 | I15: 18.75 | J15: 0 | K15: 93.75 | L15: 26.77 | M15: Priority
A16: 10348 | B16: 2024-02-16 | C16: CUST1047 | D16: Aarav Mehta | E16: North | F16: Furniture | G16: Sofa Cushion | H16: 4 | I16: 15 | J16: 0 | K16: 60 | L16: 10.89 | M16: Priority
A17: 10361 | B17: 2024-03-19 | C17: CUST1060 | D17: Isha Reddy | E17: North | F17: Stationery | G17: Notebook Pack | H17: 7 | I17: 5.5 | J17: 0 | K17: 38.5 | L17: 12.64 | M17: Standard
A18: 10139 | B18: 2024-08-08 | C18: CUST1138 | D18: Diya Joshi | E18: North | F18: Stationery | G18: Marker Set | H18: 8 | I18: 6.75 | J18: 0.1 | K18: 48.6 | L18: 14.69 | M18: Standard
A19: 10332 | B19: 2024-06-16 | C19: CUST1031 | D19: Arjun Joshi | E19: East | F19: Apparel | G19: Running Shoes | H19: 4 | I19: 55 | J19: 0 | K19: 220 | L19: 54.84 | M19: Standard
A20: 10095 | B20: 2024-08-24 | C20: CUST1094 | D20: Kavya Reddy | E20: North | F20: Furniture | G20: Filing Cabinet | H20: 5 | I20: 75.5 | J20: 0.1 | K20: 339.75 | L20: 59.6 | M20: Standard
A21: 10262 | B21: 2024-02-07 | C21: CUST1111 | D21: Priya Mehta | E21: North | F21: Stationery | G21: Gel Pen Set | H21: 7 | I21: 4.25 | J21: 0 | K21: 29.75 | L21: 11.16 | M21: Standard
A22: 10334 | B22: 2024-08-19 | C22: CUST1033 | D22: Rohan Joshi | E22: East | F22: Apparel | G22: Running Shoes | H22: 2 | I22: 55 | J22: 0 | K22: 110 | L22: 21.71 | M22: Standard
A23: 10213 | B23: 2024-05-28 | C23: CUST1062 | D23: Kavya Gupta | E23: North | F23: Stationery | G23: Notebook Pack | H23: 6 | I23: 5.5 | J23: 0.25 | K23: 24.75 | L23: 9.07 | M23: Standard
... A52: 10140 | B52: 2024-01-04 | C52: CUST1139 | D52: Vihaan Sharma | E52: South | F52: Stationery | G52: Gel Pen Set | H52: 3 | I52: 4.25 | J52: 0.1 | K52: 11.47 | L52: 3.76 | M52: Express
A53: 10112 | B53: 2024-05-31 | C53: CUST1111 | E53: East | F53: Apparel | G53: Denim Jacket | H53: 4 | I53: 42 | J53: 0 | K53: 168 | L53: 40.14 | M53: Priority
A54: 10190 | B54: 2024-10-09 | C54: CUST1039 | D54: Sai Joshi | E54: East | F54: Furniture | G54: Bookshelf | H54: 10 | I54: 65 | J54: 0 | K54: 650 | L54: 117.09 | M54: Priority
A55: 10083 | B55: 2024-04-18 | C55: CUST1082 | D55: Sai Sharma | E55: East | F55: Electronics | G55: Bluetooth Speaker | H55: 4 | I55: 34.5 | J55: 0 | K55: 138 | L55: 39.24 | M55: Express
A56: 10231 | B56: 2024-05-26 | C56: CUST1080 | D56: Diya Reddy | E56: West | F56: Furniture | G56: Study Desk | H56: 7 | I56: 120 | J56: 0.15 | K56: 714 | L56: 147.52 | M56: Express
A57: 10011 | B57: 2024-05-14 | C57: CUST1010 | D57: Arjun Nair | E57: Central | F57: Apparel | G57: Cap | H57: 7 | I57: 8 | J57: 0.15 | K57: 47.6 | L57: 9.59 | M57: Express
A58: 10269 | B58: 2024-07-13 | C58: CUST1118 | D58: Isha Gupta | E58: East | F58: Apparel | G58: Running Shoes | H58: 7 | I58: 55 | J58: 0 | K58: 385 | L58: 79.63 | M58: Express
A59: 10121 | B59: 2024-04-18 | C59: CUST1120 | D59: Riya Gupta | E59: Central | F59: Electronics | G59: Wireless Mouse | H59: 6 | I59: 12.99 | J59: 0.05 | K59: 74.04 | L59: 23.77 | M59: Standard
A60: 10230 | B60: 2024-01-24 | C60: CUST1079 | D60: Aditya Reddy | E60: West | F60: Stationery | G60: Notebook Pack | H60: 9 | I60: 5.5 | J60: 0 | K60: 49.5 | L60: 19.58 | M60: Standard
A61: 10376 | B61: 2024-09-05 | C61: CUST1075 | D61: Myra Yadav | E61: Central | F61: Stationery | G61: Notebook Pack | H61: 9 | I61: 5.5 | J61: 0 | K61: 49.5 | L61: 15.07 | M61: Standard
A62: 10217 | B62: 2024-10-20 | C62: CUST1066 | D62: Vivaan Yadav | F62: Electronics | G62: Bluetooth Speaker | H62: 7 | I62: 34.5 | J62: 0 | K62: 241.5 | L62: 76.42 | M62: Express
A63: 10268 | B63: 2024-11-16 | C63: CUST1117 | D63: Diya Mehta | E63: West | F63: Furniture | G63: Filing Cabinet | H63: 2 | I63: 75.5 | J63: 0 | K63: 151 | L63: 25.59 | M63: Priority
A64: 10252 | B64: 2024-09-28 | C64: CUST1101 | D64: Sai Verma | E64: East | F64: Stationery | G64: Notebook Pack | H64: 9 | I64: 5.5 | J64: 0.2 | K64: 39.6 | L64: 15.13 | M64: Standard
A65: 10343 | B65: 2024-07-02 | C65: CUST1042 | D65: Sai Sharma | E65: West | F65: Apparel | G65: Running Shoes | H65: 10 | I65: 55 | J65: 0.15 | K65: 467.5 | L65: 99.41 | M65: Express
A66: 10345 | B66: 2024-02-21 | C66: CUST1044 | D66: Krishna Joshi | E66: South | F66: Furniture | G66: Bookshelf | H66: 9 | I66: 65 | J66: 0 | K66: 585 | L66: 113.64 | M66: Express
A67: 10248 | B67: 2024-09-12 | C67: CUST1097 | D67: Ananya Patel | E67: Central | F67: Stationery | G67: Sticky Notes | H67: 8 | I67: 3.1 | J67: 0.25 | K67: 18.6 | L67: 6.43 | M67: Standard
A68: 10056 | B68: 2024-05-26 | C68: CUST1055 | D68: Krishna Yadav | E68: South | F68: Stationery | G68: Sticky Notes | H68: 6 | I68: 3.1 | J68: 0 | K68: 18.6 | L68: 5.8 | M68: Priority
A69: 10143 | B69: 2024-11-23 | C69: CUST1142 | D69: Sai Joshi | E69: West | F69: Stationery | G69: Notebook Pack | H69: 7 | I69: 5.5 | J69: 0 | K69: 38.5 | L69: 15.36 | M69: Express
A70: 10317 | B70: 2024-06-16 | C70: CUST1016 | D70: Aditya Yadav | E70: West | F70: Electronics | G70: USB-C Hub | H70: 7 | I70: 22 | J70: 0.05 | K70: 146.3 | L70: 35.53 | M70: Standard
A71: 10271 | B71: 2024-05-23 | C71: CUST1120 | D71: Anika Patel | E71: West | F71: Stationery | G71: Notebook Pack | H71: 10 | I71: 5.5 | J71: 0.05 | K71: 52.25 | L71: 18.79 | M71: Priority
A72: 10200 | B72: 2024-07-06 | C72: CUST1049 | D72: Rohan Verma | E72: North | F72: Apparel | G72: Cotton T-Shirt | H72: 10 | I72: 9.99 | J72: 0.05 | K72: 94.91 | L72: 20.02 | M72: Express
A73: 10267 | B73: 2024-03-26 | C73: CUST1116 | D73: Ananya Singh | F73: Stationery | G73: Whiteboard | H73: 5 | I73: 27 | J73: 0.25 | K73: 101.25 | L73: 38.44 | M73: Standard
A74: 10145 | B74: 2024-07-21 | C74: CUST1144 | D74: Vihaan Nair | E74: East | F74: Stationery | G74: Gel Pen Set | H74: 6 | I74: 4.25 | J74: 0 | K74: 25.5 | L74: 7.79 | M74: Priority
A75: 10002 | B75: 2024-10-29 | C75: CUST1001 | D75: Isha Sharma | E75: West | F75: Electronics | G75: Wireless Mouse | H75: 2 | I75: 12.99 | J75: 0.05 | K75: 24.68 | L75: 6.36 | M75: Priority
A76: 10041 | B76: 2024-12-25 | C76: CUST1040 | D76: Aadhya Mehta | E76: North | F76: Apparel | G76: Cotton T-Shirt | H76: 8 | I76: 9.99 | J76: 0.05 | K76: 75.92 | L76: 15.2 | M76: Express
A77: 10367 | B77: 2024-01-18 | C77: CUST1066 | D77: Sai Gupta | E77: Central | F77: Furniture | G77: Office Chair | H77: 8 | I77: 89 | J77: 0 | K77: 712 | L77: 145.43 | M77: Standard
A78: 10009 | B78: 2024-12-16 | C78: CUST1008 | D78: Aditya Gupta | E78: East | F78: Electronics | G78: Bluetooth Speaker | H78: 1 | I78: 34.5 | J78: 0.15 | K78: 29.32 | L78: 7.97 | M78: Priority
A79: 10342 | B79: 2024-05-23 | C79: CUST1041 | D79: Anika Sharma | E79: West | F79: Furniture | G79: Filing Cabinet | H79: 4 | I79: 75.5 | J79: 0.05 | K79: 286.9 | L79: 53.67 | M79: Express
A80: 10186 | B80: 2024-03-07 | C80: CUST1035 | D80: Kavya Nair | E80: Central | F80: Electronics | G80: Wireless Mouse | H80: 5 | I80: 12.99 | J80: 0.2 | K80: 51.96 | L80: 16.73 | M80: Express
A81: 10202 | B81: 2024-06-22 | C81: CUST1051 | D81: Vivaan Sharma | E81: Central | F81: Stationery | G81: Gel Pen Set | H81: 4 | I81: 4.25 | J81: 0.2 | K81: 13.6 | L81: 4.76 | M81: Standard
A82: 10101 | B82: 2024-03-14 | C82: CUST1100 | D82: Diya Verma | E82: West | F82: Furniture | G82: Office Chair | H82: 8 | I82: 89 | J82: 0.1 | K82: 640.8 | L82: 109.76 | M82: Express
A83: 10063 | B83: 2024-10-03 | C83: CUST1062 | D83: Krishna Gupta | E83: North | F83: Stationery | G83: Gel Pen Set | H83: 2 | I83: 4.25 | J83: 0 | K83: 8.5 | L83: 3.2 | M83: Standard
A84: 10280 | B84: 2024-08-12 | C84: CUST1129 | D84: Vihaan Sharma | E84: West | F84: Stationery | G84: Notebook Pack | H84: 5 | I84: 5.5 | J84: 0 | K84: 27.5 | L84: 10.52 | M84: Express
A85: 10326 | B85: 2024-10-10 | C85: CUST1025 | D85: Rohan Joshi | E85: West | F85: Electronics | G85: USB-C Hub | H85: 4 | I85: 22 | J85: 0.1 | K85: 79.2 | L85: 22.6 | M85: Standard
... A103: 10017 | B103: 2024-05-03 | C103: CUST1016 | D103: Anika Patel | E103: Central | F103: Electronics | G103: Wireless Mouse | H103: 8 | I103: 12.99 | J103: 0 | K103: 103.92 | L103: 33.27 | M103: Standard
A104: 10155 | B104: 2024-06-07 | C104: CUST1004 | D104: Priya Patel | F104: Furniture | G104: Sofa Cushion | H104: 2 | I104: 15 | J104: 0.1 | K104: 27 | L104: 4.95 | M104: Priority
A105: 10022 | B105: 2024-10-19 | C105: CUST1021 | D105: Vihaan Yadav | E105: Central | F105: Apparel | G105: Denim Jacket | H105: 8 | I105: 42 | J105: 0.2 | K105: 268.8 | L105: 53.64 | M105: Express
A106: 10106 | B106: 2024-03-14 | C106: CUST1105 | D106: Aadhya Singh | E106: South | F106: Apparel | G106: Running Shoes | H106: 8 | I106: 55 | J106: 0.1 | K106: 396 | L106: 91.48 | M106: Priority
A107: 10084 | B107: 2024-08-18 | C107: CUST1083 | D107: Rohan Reddy | E107: Central | F107: Apparel | G107: Running Shoes | H107: 1 | I107: 55 | J107: 0.05 | K107: 52.25 | L107: 10.76 | M107: Standard
A108: 10227 | B108: 2024-09-15 | C108: CUST1076 | D108: Reyansh Joshi | E108: South | F108: Furniture | G108: Study Desk | H108: 6 | I108: 120 | J108: 0.25 | K108: 540 | L108: 86.01 | M108: Express
A109: 10283 | B109: 2024-10-30 | C109: CUST1132 | D109: Aditya Joshi | E109: West | F109: Apparel | G109: Cotton T-Shirt | H109: 4 | I109: 9.99 | J109: 0.05 | K109: 37.96 | L109: 7.8 | M109: Standard
A110: 10324 | B110: 2024-05-07 | C110: CUST1023 | D110: Vivaan Patel | E110: West | F110: Stationery | G110: Sticky Notes | H110: 2 | I110: 3.1 | J110: 0.15 | K110: 5.27 | L110: 1.63 | M110: Standard
A111: 10089 | B111: 2024-03-30 | C111: CUST1088 | D111: Kavya Verma | E111: West | F111: Apparel | G111: Running Shoes | H111: 3 | I111: 55 | J111: 0.2 | K111: 132 | L111: 30.21 | M111: Express
A112: 10356 | B112: 2024-07-12 | C112: CUST1055 | D112: Aditya Sharma | E112: East | F112: Apparel | G112: Cotton T-Shirt | H112: 8 | I112: 9.99 | J112: 0.05 | K112: 75.92 | L112: 15.01 | M112: Express
A113: 10211 | B113: 2024-06-01 | C113: CUST1060 | D113: Ananya Nair | E113: South | F113: Stationery | G113: Sticky Notes | H113: 4 | I113: 3.1 | J113: 0.25 | K113: 9.3 | L113: 3.08 | M113: Priority
A114: 10125 | B114: 2024-02-02 | C114: CUST1124 | D114: Krishna Joshi | E114: West | F114: Apparel | G114: Running Shoes | H114: 9 | I114: 55 | J114: 0 | K114: 495 | L114: 107.33 | M114: Standard
A115: 10288 | B115: 2024-11-21 | C115: CUST1137 | D115: Sai Mehta | E115: Central | F115: Furniture | G115: Sofa Cushion | H115: 3 | I115: 15 | J115: 0.25 | K115: 33.75 | L115: 5.69 | M115: Express
A116: 10314 | B116: 2024-10-06 | C116: CUST1013 | D116: Reyansh Sharma | E116: South | F116: Apparel | G116: Cotton T-Shirt | H116: 1 | I116: 9.99 | J116: 0 | K116: 9.99 | L116: 1.88 | M116: Standard
... A182: 10218 | B182: 2024-04-05 | C182: CUST1067 | D182: Priya Singh | E182: East | F182: Electronics | G182: Wireless Mouse | H182: 5 | I182: 12.99 | J182: 0 | K182: 64.95 | L182: 20.52 | M182: Express
A183: 10320 | B183: 2024-06-20 | C183: CUST1019 | D183: Riya Verma | F183: Stationery | G183: Marker Set | H183: 2 | I183: 6.75 | J183: 0.1 | K183: 12.15 | L183: 4.52 | M183: Express
A184: 10073 | B184: 2024-05-03 | C184: CUST1072 | D184: Kavya Reddy | E184: West | F184: Apparel | G184: Cap | H184: 4 | I184: 8 | J184: 0.25 | K184: 24 | L184: 5.51 | M184: Standard
A185: 10031 | B185: 2024-05-13 | C185: CUST1030 | D185: Rohan Reddy | E185: South | F185: Stationery | G185: Gel Pen Set | H185: 5 | I185: 4.25 | J185: 0.2 | K185: 17 | L185: 5.29 | M185: Express
A186: 10159 | B186: 2024-08-12 | C186: CUST1008 | D186: Aadhya Gupta | E186: North | F186: Apparel | G186: Running Shoes | H186: 4 | I186: 55 | J186: 0.25 | K186: 165 | L186: 37.5 | M186: Priority
A187: 10131 | B187: 2024-02-13 | C187: CUST1130 | D187: Riya Nair | E187: North | F187: Apparel | G187: Cotton T-Shirt | H187: 6 | I187: 9.99 | J187: 0 | K187: 59.94 | L187: 13.41 | M187: Priority
A188: 10027 | B188: 2024-05-26 | C188: CUST1026 | D188: Vivaan Joshi | E188: West | F188: Apparel | G188: Denim Jacket | H188: 4 | I188: 42 | J188: 0.1 | K188: 151.2 | L188: 30.45 | M188: Priority
A189: 10323 | B189: 2024-08-29 | C189: CUST1022 | D189: Saanvi Gupta | E189: East | F189: Apparel | G189: Denim Jacket | H189: 3 | I189: 42 | J189: 0 | K189: 126 | L189: 28.16 | M189: Express
A190: 10036 | B190: 2024-09-07 | C190: CUST1035 | D190: Priya Patel | E190: East | F190: Electronics | G190: Wireless Mouse | H190: 7 | I190: 12.99 | J190: 0.1 | K190: 81.84 | L190: 19.78 | M190: Priority
A191: 10204 | B191: 2024-07-20 | C191: CUST1053 | D191: Rohan Reddy | F191: Stationery | G191: Marker Set | H191: 6 | I191: 6.75 | J191: 0.25 | K191: 30.38 | L191: 11.3 | M191: Standard
A192: 10156 | B192: 2024-12-25 | C192: CUST1005 | D192: Rohan Patel | E192: Central | F192: Electronics | G192: Laptop Stand | H192: 9 | I192: 18.75 | J192: 0.15 | K192: 143.44 | L192: 34.36 | M192: Standard
A193: 10259 | B193: 2024-10-03 | C193: CUST1108 | D193: Saanvi Gupta | E193: East | F193: Apparel | G193: Denim Jacket | H193: 2 | I193: 42 | J193: 0.15 | K193: 71.4 | L193: 13.6 | M193: Standard
A194: 10070 | B194: 2024-09-04 | C194: CUST1069 | D194: Aditya Singh | E194: West | F194: Apparel | G194: Cap | H194: 5 | I194: 8 | J194: 0.15 | K194: 34 | L194: 8.27 | M194: Express
A195: 10364 | B195: 2024-08-16 | C195: CUST1063 | D195: Ishaan Joshi | E195: North | F195: Stationery | G195: Whiteboard | H195: 8 | I195: 27 | J195: 0.1 | K195: 194.4 | L195: 62.45 | M195: Standard
A196: 10195 | B196: 2024-03-07 | C196: CUST1044 | D196: Aadhya Gupta | E196: East | F196: Electronics | G196: USB-C Hub | H196: 4 | I196: 22 | J196: 0.25 | K196: 66 | L196: 16.39 | M196: Standard
A197: 10026 | B197: 2024-09-05 | C197: CUST1025 | D197: Diya Singh | E197: West | F197: Furniture | G197: Filing Cabinet | H197: 1 | I197: 75.5 | J197: 0 | K197: 75.5 | L197: 13.1 | M197: Express
A198: 10219 | B198: 2024-11-24 | C198: CUST1068 | D198: Vihaan Mehta | E198: Central | F198: Apparel | G198: Denim Jacket | H198: 9 | I198: 42 | J198: 0.25 | K198: 283.5 | L198: 58.12 | M198: Standard
A199: 10331 | B199: 2024-10-17 | C199: CUST1030 | D199: Priya Yadav | E199: North | F199: Apparel | G199: Denim Jacket | H199: 4 | I199: 42 | J199: 0.1 | K199: 151.2 | L199: 30.88 | M199: Priority
A200: 10329 | B200: 2024-09-28 | C200: CUST1028 | D200: Aditya Sharma | E200: South | F200: Apparel | G200: Wool Sweater | H200: 1 | I200: 38.5 | J200: 0 | K200: 38.5 | L200: 9.01 | M200: Standard
A201: 10276 | B201: 2024-12-12 | C201: CUST1125 | D201: Krishna Nair | E201: West | F201: Stationery | G201: Whiteboard | H201: 2 | I201: 27 | J201: 0 | K201: 54 | L201: 16.62 | M201: Priority
A202: 10310 | B202: 2024-10-28 | C202: CUST1009 | D202: Aditya Gupta | E202: West | F202: Stationery | G202: Whiteboard | H202: 6 | I202: 27 | J202: 0 | K202: 162 | L202: 52.41 | M202: Priority
A203: 10332 | B203: 2024-06-16 | C203: CUST1031 | D203: Arjun Joshi | E203: East | F203: Apparel | G203: Running Shoes | H203: 4 | I203: 55 | J203: 0 | K203: 220 | L203: 54.84 | M203: Standard
... A217: 10289 | B217: 2024-11-13 | C217: CUST1138 | D217: Diya Nair | E217: North | F217: Stationery | G217: Notebook Pack | H217: 8 | I217: 5.5 | J217: 0 | K217: 44 | L217: 13.99 | M217: Priority
A218: 10239 | B218: 2024-01-25 | C218: CUST1088 | D218: Rohan Yadav | F218: Apparel | G218: Cap | H218: 6 | I218: 8 | J218: 0.2 | K218: 38.4 | L218: 8.22 | M218: Standard
A219: 10210 | B219: 2024-06-24 | C219: CUST1059 | D219: Krishna Singh | E219: Central | F219: Stationery | G219: Sticky Notes | H219: 10 | I219: 3.1 | J219: 0.25 | K219: 23.25 | L219: 7.39 | M219: Priority
A220: 10168 | B220: 2024-05-03 | C220: CUST1017 | D220: Saanvi Patel | E220: South | F220: Stationery | G220: Whiteboard | H220: 1 | I220: 27 | J220: 0.15 | K220: 22.95 | L220: 7.41 | M220: Priority
A221: 10319 | B221: 2024-09-11 | C221: CUST1018 | D221: Ishaan Verma | E221: East | F221: Stationery | G221: Gel Pen Set | H221: 6 | I221: 4.25 | J221: 0 | K221: 25.5 | L221: 9.59 | M221: Standard
A222: 10341 | B222: 2024-11-10 | C222: CUST1040 | D222: Kavya Sharma | E222: Central | F222: Furniture | G222: Bookshelf | H222: 8 | I222: 65 | J222: 0.2 | K222: 416 | L222: 83.48 | M222: Standard
A223: 10222 | B223: 2024-09-01 | C223: CUST1071 | D223: Ishaan Mehta | E223: East | F223: Furniture | G223: Office Chair | H223: 5 | I223: 89 | J223: 0.2 | K223: 356 | L223: 59 | M223: Express
A224: 10263 | B224: 2024-02-16 | C224: CUST1112 | D224: Aditya Patel | E224: North | F224: Stationery | G224: Whiteboard | H224: 6 | I224: 27 | J224: 0.1 | K224: 145.8 | L224: 44.94 | M224: Express
...

Sheet Cleaned_Data
A1: Cleaned_Data — Task 2 output (deduped, missing rows removed, types formatted)
A3: OrderID | B3: OrderDate | C3: CustomerID | D3: CustomerName | E3: Region | F3: Category | G3: Product | H3: Quantity | I3: UnitPrice | J3: Discount | K3: Sales | L3: Profit | M3: ShipMode | N3: OrderMonth
A4: 10303 | B4: 2024-01-01 | C4: CUST1002 | D4: Ishaan Verma | E4: West | F4: Furniture | G4: Study Desk | H4: 5 | I4: 120 | J4: 0 | K4: =ROUND(H4*I4*(1-J4),2) -> 600 | L4: =ROUND(K4*VLOOKUP(F4,Reference!$A$4:$B$7,2,FALSE()),2) -> 108 | M4: Priority | N4: =TEXT(B4,"mmm-yyyy") -> Jan-2024
A5: 10092 | B5: 2024-01-01 | C5: CUST1091 | D5: Isha Reddy | E5: Central | F5: Apparel | G5: Wool Sweater | H5: 1 | I5: 38.5 | J5: 0.05 | K5: =ROUND(H5*I5*(1-J5),2) -> 36.58 | L5: =ROUND(K5*VLOOKUP(F5,Reference!$A$4:$B$7,2,FALSE()),2) -> 8.05 | M5: Priority | N5: =TEXT(B5,"mmm-yyyy") -> Jan-2024
A6: 10016 | B6: 2024-01-01 | C6: CUST1015 | D6: Rohan Gupta | E6: Central | F6: Stationery | G6: Whiteboard | H6: 1 | I6: 27 | J6: 0 | K6: =ROUND(H6*I6*(1-J6),2) -> 27 | L6: =ROUND(K6*VLOOKUP(F6,Reference!$A$4:$B$7,2,FALSE()),2) -> 9.45 | M6: Standard | N6: =TEXT(B6,"mmm-yyyy") -> Jan-2024
A7: 10140 | B7: 2024-01-04 | C7: CUST1139 | D7: Vihaan Sharma | E7: South | F7: Stationery | G7: Gel Pen Set | H7: 3 | I7: 4.25 | J7: 0.1 | K7: =ROUND(H7*I7*(1-J7),2) -> 11.48 | L7: =ROUND(K7*VLOOKUP(F7,Reference!$A$4:$B$7,2,FALSE()),2) -> 4.02 | M7: Express | N7: =TEXT(B7,"mmm-yyyy") -> Jan-2024
A8: 10079 | B8: 2024-01-07 | C8: CUST1078 | D8: Vivaan Singh | E8: Central | F8: Stationery | G8: Whiteboard | H8: 8 | I8: 27 | J8: 0.25 | K8: =ROUND(H8*I8*(1-J8),2) -> 162 | L8: =ROUND(K8*VLOOKUP(F8,Reference!$A$4:$B$7,2,FALSE()),2) -> 56.7 | M8: Express | N8: =TEXT(B8,"mmm-yyyy") -> Jan-2024
A9: 10370 | B9: 2024-01-07 | C9: CUST1069 | D9: Riya Joshi | E9: Central | F9: Apparel | G9: Cotton T-Shirt | H9: 7 | I9: 9.99 | J9: 0 | K9: =ROUND(H9*I9*(1-J9),2) -> 69.93 | L9: =ROUND(K9*VLOOKUP(F9,Reference!$A$4:$B$7,2,FALSE()),2) -> 15.38 | M9: Standard | N9: =TEXT(B9,"mmm-yyyy") -> Jan-2024
A10: 10337 | B10: 2024-01-07 | C10: CUST1036 | D10: Aditya Joshi | E10: North | F10: Furniture | G10: Study Desk | H10: 4 | I10: 120 | J10: 0.2 | K10: =ROUND(H10*I10*(1-J10),2) -> 384 | L10: =ROUND(K10*VLOOKUP(F10,Reference!$A$4:$B$7,2,FALSE()),2) -> 69.12 | M10: Priority | N10: =TEXT(B10,"mmm-yyyy") -> Jan-2024
A11: 10374 | B11: 2024-01-11 | C11: CUST1073 | D11: Vihaan Gupta | E11: East | F11: Stationery | G11: Sticky Notes | H11: 5 | I11: 3.1 | J11: 0.25 | K11: =ROUND(H11*I11*(1-J11),2) -> 11.63 | L11: =ROUND(K11*VLOOKUP(F11,Reference!$A$4:$B$7,2,FALSE()),2) -> 4.07 | M11: Standard | N11: =TEXT(B11,"mmm-yyyy") -> Jan-2024
A12: 10357 | B12: 2024-01-11 | C12: CUST1056 | D12: Diya Patel | E12: East | F12: Stationery | G12: Notebook Pack | H12: 2 | I12: 5.5 | J12: 0.15 | K12: =ROUND(H12*I12*(1-J12),2) -> 9.35 | L12: =ROUND(K12*VLOOKUP(F12,Reference!$A$4:$B$7,2,FALSE()),2) -> 3.27 | M12: Priority | N12: =TEXT(B12,"mmm-yyyy") -> Jan-2024
A13: 10020 | B13: 2024-01-11 | C13: CUST1019 | D13: Vivaan Gupta | E13: Central | F13: Furniture | G13: Sofa Cushion | H13: 4 | I13: 15 | J13: 0 | K13: =ROUND(H13*I13*(1-J13),2) -> 60 | L13: =ROUND(K13*VLOOKUP(F13,Reference!$A$4:$B$7,2,FALSE()),2) -> 10.8 | M13: Standard | N13: =TEXT(B13,"mmm-yyyy") -> Jan-2024
A14: 10061 | B14: 2024-01-14 | C14: CUST1060 | D14: Diya Mehta | E14: North | F14: Apparel | G14: Denim Jacket | H14: 8 | I14: 42 | J14: 0 | K14: =ROUND(H14*I14*(1-J14),2) -> 336 | L14: =ROUND(K14*VLOOKUP(F14,Reference!$A$4:$B$7,2,FALSE()),2) -> 73.92 | M14: Standard | N14: =TEXT(B14,"mmm-yyyy") -> Jan-2024
A15: 10088 | B15: 2024-01-14 | C15: CUST1087 | D15: Ishaan Joshi | E15: North | F15: Furniture | G15: Sofa Cushion | H15: 10 | I15: 15 | J15: 0 | K15: =ROUND(H15*I15*(1-J15),2) -> 150 | L15: =ROUND(K15*VLOOKUP(F15,Reference!$A$4:$B$7,2,FALSE()),2) -> 27 | M15: Standard | N15: =TEXT(B15,"mmm-yyyy") -> Jan-2024
... A369: 10078 | B369: 2024-12-28 | C369: CUST1077 | D369: Arjun Reddy | E369: Central | F369: Furniture | G369: Bookshelf | H369: 1 | I369: 65 | J369: 0 | K369: =ROUND(H369*I369*(1-J369),2) -> 65 | L369: =ROUND(K369*VLOOKUP(F369,Reference!$A$4:$B$7,2,FALSE()),2) -> 11.7 | M369: Standard | N369: =TEXT(B369,"mmm-yyyy") -> Dec-2024

Sheet Summary_Analysis
A1: Summary_Analysis — Task 3: Pivot-style summaries (SUMIFS/COUNTIFS)
A3: Region-wise Summary
A4: Region | B4: Total Sales | C4: Total Profit | D4: Order Count | E4: Avg Order Value
A5: North | B5: =SUMIFS(Cleaned_Data!$K$4:$K$369,Cleaned_Data!$E$4:$E$369,A5) -> 12826.57 | C5: =SUMIFS(Cleaned_Data!$L$4:$L$369,Cleaned_Data!$E$4:$E$369,A5) -> 2839.25 | D5: =COUNTIFS(Cleaned_Data!$E$4:$E$369,A5) -> 75 | E5: =IFERROR(B5/D5,0) -> 171.02093
A6: South | B6: =SUMIFS(Cleaned_Data!$K$4:$K$369,Cleaned_Data!$E$4:$E$369,A6) -> 12192.13 | C6: =SUMIFS(Cleaned_Data!$L$4:$L$369,Cleaned_Data!$E$4:$E$369,A6) -> 2580.52 | D6: =COUNTIFS(Cleaned_Data!$E$4:$E$369,A6) -> 65 | E6: =IFERROR(B6/D6,0) -> 187.57123
A7: East | B7: =SUMIFS(Cleaned_Data!$K$4:$K$369,Cleaned_Data!$E$4:$E$369,A7) -> 10840.84 | C7: =SUMIFS(Cleaned_Data!$L$4:$L$369,Cleaned_Data!$E$4:$E$369,A7) -> 2442.2 | D7: =COUNTIFS(Cleaned_Data!$E$4:$E$369,A7) -> 75 | E7: =IFERROR(B7/D7,0) -> 144.54453
A8: West | B8: =SUMIFS(Cleaned_Data!$K$4:$K$369,Cleaned_Data!$E$4:$E$369,A8) -> 13643.61 | C8: =SUMIFS(Cleaned_Data!$L$4:$L$369,Cleaned_Data!$E$4:$E$369,A8) -> 3005.55 | D8: =COUNTIFS(Cleaned_Data!$E$4:$E$369,A8) -> 79 | E8: =IFERROR(B8/D8,0) -> 172.70392
A9: Central | B9: =SUMIFS(Cleaned_Data!$K$4:$K$369,Cleaned_Data!$E$4:$E$369,A9) -> 12435.63 | C9: =SUMIFS(Cleaned_Data!$L$4:$L$369,Cleaned_Data!$E$4:$E$369,A9) -> 2714.84 | D9: =COUNTIFS(Cleaned_Data!$E$4:$E$369,A9) -> 72 | E9: =IFERROR(B9/D9,0) -> 172.71708
A12: Category-wise Summary
A13: Category | B13: Total Sales | C13: Total Profit | D13: Order Count | E13: Avg Order Value
A14: Electronics | B14: =SUMIFS(Cleaned_Data!$K$4:$K$369,Cleaned_Data!$F$4:$F$369,A14) -> 9528.89 | C14: =SUMIFS(Cleaned_Data!$L$4:$L$369,Cleaned_Data!$F$4:$F$369,A14) -> 2668.09 | D14: =COUNTIFS(Cleaned_Data!$F$4:$F$369,A14) -> 81 | E14: =IFERROR(B14/D14,0) -> 117.64062
A15: Furniture | B15: =SUMIFS(Cleaned_Data!$K$4:$K$369,Cleaned_Data!$F$4:$F$369,A15) -> 30998.36 | C15: =SUMIFS(Cleaned_Data!$L$4:$L$369,Cleaned_Data!$F$4:$F$369,A15) -> 5579.71 | D15: =COUNTIFS(Cleaned_Data!$F$4:$F$369,A15) -> 78 | E15: =IFERROR(B15/D15,0) -> 397.41487
A16: Stationery | B16: =SUMIFS(Cleaned_Data!$K$4:$K$369,Cleaned_Data!$F$4:$F$369,A16) -> 4798.89 | C16: =SUMIFS(Cleaned_Data!$L$4:$L$369,Cleaned_Data!$F$4:$F$369,A16) -> 1679.74 | D16: =COUNTIFS(Cleaned_Data!$F$4:$F$369,A16) -> 100 | E16: =IFERROR(B16/D16,0) -> 47.9889
A17: Apparel | B17: =SUMIFS(Cleaned_Data!$K$4:$K$369,Cleaned_Data!$F$4:$F$369,A17) -> 16612.64 | C17: =SUMIFS(Cleaned_Data!$L$4:$L$369,Cleaned_Data!$F$4:$F$369,A17) -> 3654.82 | D17: =COUNTIFS(Cleaned_Data!$F$4:$F$369,A17) -> 107 | E17: =IFERROR(B17/D17,0) -> 155.25832
A20: Month-wise Sales Trend (2024)
A21: Month | B21: Total Sales | C21: Total Profit
A22: Jan-2024 | B22: =SUMIFS(Cleaned_Data!$K$4:$K$369,Cleaned_Data!$N$4:$N$369,A22) -> 4785.91 | C22: =SUMIFS(Cleaned_Data!$L$4:$L$369,Cleaned_Data!$N$4:$N$369,A22) -> 1044.89
A23: Feb-2024 | B23: =SUMIFS(Cleaned_Data!$K$4:$K$369,Cleaned_Data!$N$4:$N$369,A23) -> 6279.09 | C23: =SUMIFS(Cleaned_Data!$L$4:$L$369,Cleaned_Data!$N$4:$N$369,A23) -> 1313.81
A24: Mar-2024 | B24: =SUMIFS(Cleaned_Data!$K$4:$K$369,Cleaned_Data!$N$4:$N$369,A24) -> 4719.04 | C24: =SUMIFS(Cleaned_Data!$L$4:$L$369,Cleaned_Data!$N$4:$N$369,A24) -> 1098.14
A25: Apr-2024 | B25: =SUMIFS(Cleaned_Data!$K$4:$K$369,Cleaned_Data!$N$4:$N$369,A25) -> 4198.48 | C25: =SUMIFS(Cleaned_Data!$L$4:$L$369,Cleaned_Data!$N$4:$N$369,A25) -> 956.52
A26: May-2024 | B26: =SUMIFS(Cleaned_Data!$K$4:$K$369,Cleaned_Data!$N$4:$N$369,A26) -> 4189.11 | C26: =SUMIFS(Cleaned_Data!$L$4:$L$369,Cleaned_Data!$N$4:$N$369,A26) -> 941.93
A27: Jun-2024 | B27: =SUMIFS(Cleaned_Data!$K$4:$K$369,Cleaned_Data!$N$4:$N$369,A27) -> 6150.22 | C27: =SUMIFS(Cleaned_Data!$L$4:$L$369,Cleaned_Data!$N$4:$N$369,A27) -> 1392.74
A28: Jul-2024 | B28: =SUMIFS(Cleaned_Data!$K$4:$K$369,Cleaned_Data!$N$4:$N$369,A28) -> 4279.26 | C28: =SUMIFS(Cleaned_Data!$L$4:$L$369,Cleaned_Data!$N$4:$N$369,A28) -> 968.08
A29: Aug-2024 | B29: =SUMIFS(Cleaned_Data!$K$4:$K$369,Cleaned_Data!$N$4:$N$369,A29) -> 5068.45 | C29: =SUMIFS(Cleaned_Data!$L$4:$L$369,Cleaned_Data!$N$4:$N$369,A29) -> 1123.59
A30: Sep-2024 | B30: =SUMIFS(Cleaned_Data!$K$4:$K$369,Cleaned_Data!$N$4:$N$369,A30) -> 7371.42 | C30: =SUMIFS(Cleaned_Data!$L$4:$L$369,Cleaned_Data!$N$4:$N$369,A30) -> 1526.01
A31: Oct-2024 | B31: =SUMIFS(Cleaned_Data!$K$4:$K$369,Cleaned_Data!$N$4:$N$369,A31) -> 4600.5 | C31: =SUMIFS(Cleaned_Data!$L$4:$L$369,Cleaned_Data!$N$4:$N$369,A31) -> 971.88
A32: Nov-2024 | B32: =SUMIFS(Cleaned_Data!$K$4:$K$369,Cleaned_Data!$N$4:$N$369,A32) -> 6127.85 | C32: =SUMIFS(Cleaned_Data!$L$4:$L$369,Cleaned_Data!$N$4:$N$369,A32) -> 1288.64
A33: Dec-2024 | B33: =SUMIFS(Cleaned_Data!$K$4:$K$369,Cleaned_Data!$N$4:$N$369,A33) -> 4169.45 | C33: =SUMIFS(Cleaned_Data!$L$4:$L$369,Cleaned_Data!$N$4:$N$369,A33) -> 956.13

Sheet Formulas_Demo
A1: Formulas_Demo — Task 4: Advanced Formulas (VLOOKUP, INDEX-MATCH, nested IF, IFERROR)
A3: 1) VLOOKUP — get Category Margin % from the Reference sheet
A4: Type a category: | B4: Electronics
A5: Formula (in B5): | B5: =IFERROR(VLOOKUP(B4,Reference!$A$4:$B$7,2,FALSE()),"Not found") -> 0.28
A6: Result: | B6: =B5 -> 0.28
A9: 2) INDEX-MATCH — get Region Sales Target from the Reference sheet
A10: Type a region: | B10: North
A11: Formula (in B11): | B11: =INDEX(Reference!$E$4:$E$8,MATCH(B10,Reference!$D$4:$D$8,0)) -> 3000
A12: Why INDEX-MATCH here: | B12: Works left-to-right or right-to-left (VLOOKUP can't look right-to-find-left); faster on large sheets.
A15: 3) Nested IF — classify order performance from the first 10 cleaned orders
A16: OrderID | B16: Sales | C16: Performance Tier | D16: Rule
A17: =Cleaned_Data!A4 -> 10303 | B17: =Cleaned_Data!K4 -> 600 | C17: =IF(B17>150,"High",IF(B17>75,"Medium","Low")) -> High | D17: Rule: >150 High, >75 Medium, else Low
A18: =Cleaned_Data!A5 -> 10092 | B18: =Cleaned_Data!K5 -> 36.58 | C18: =IF(B18>150,"High",IF(B18>75,"Medium","Low")) -> Low
A19: =Cleaned_Data!A6 -> 10016 | B19: =Cleaned_Data!K6 -> 27 | C19: =IF(B19>150,"High",IF(B19>75,"Medium","Low")) -> Low
A20: =Cleaned_Data!A7 -> 10140 | B20: =Cleaned_Data!K7 -> 11.48 | C20: =IF(B20>150,"High",IF(B20>75,"Medium","Low")) -> Low
A21: =Cleaned_Data!A8 -> 10079 | B21: =Cleaned_Data!K8 -> 162 | C21: =IF(B21>150,"High",IF(B21>75,"Medium","Low")) -> High
A22: =Cleaned_Data!A9 -> 10370 | B22: =Cleaned_Data!K9 -> 69.93 | C22: =IF(B22>150,"High",IF(B22>75,"Medium","Low")) -> Low
A23: =Cleaned_Data!A10 -> 10337 | B23: =Cleaned_Data!K10 -> 384 | C23: =IF(B23>150,"High",IF(B23>75,"Medium","Low")) -> High
A24: =Cleaned_Data!A11 -> 10374 | B24: =Cleaned_Data!K11 -> 11.63 | C24: =IF(B24>150,"High",IF(B24>75,"Medium","Low")) -> Low
A25: =Cleaned_Data!A12 -> 10357 | B25: =Cleaned_Data!K12 -> 9.35 | C25: =IF(B25>150,"High",IF(B25>75,"Medium","Low")) -> Low
A26: =Cleaned_Data!A13 -> 10020 | B26: =Cleaned_Data!K13 -> 60 | C26: =IF(B26>150,"High",IF(B26>75,"Medium","Low")) -> Low

Sheet Dashboard
A1: Sales Dashboard — Task 5 & 6: Charts, Conditional Formatting, KPIs, Filter
A3: Total Sales | C3: Total Profit | E3: Total Orders | G3: Avg Order Value
A4: =SUM(Cleaned_Data!K4:K369) -> 61938.78 | C4: =SUM(Cleaned_Data!L4:L369) -> 13582.36 | E4: =COUNT(Cleaned_Data!A4:A369) -> 366 | G4: =SUM(Cleaned_Data!K4:K369)/COUNT(Cleaned_Data!A4:A369) -> 169.23164
A6: Interactive Filter
A7: Select Region: | B7: All
A8: Filtered Sales: | B8: =IF(B7="All",SUM(Cleaned_Data!K4:K369),SUMIFS(Cleaned_Data!K4:K369,Cleaned_Data!E4:E369,B7)) -> 61938.78
A9: Filtered Orders: | B9: =IF(B7="All",COUNT(Cleaned_Data!A4:A369),COUNTIFS(Cleaned_Data!E4:E369,B7)) -> 366
A10: Note: | B10: This dropdown drives the two cells above via IF/SUMIFS. For a real click-and-filter Slicer, follow Documentation sheet steps.
A12: Chart Source: Region Sales | D12: Chart Source: Category Sales | G12: Chart Source: Monthly Trend
A13: Region | B13: Sales | D13: Category | E13: Sales | G13: Month | H13: Sales
A14: =Summary_Analysis!A5 -> North | B14: =Summary_Analysis!B5 -> 12826.57 | D14: =Summary_Analysis!A14 -> Electronics | E14: =Summary_Analysis!B14 -> 9528.89 | G14: =Summary_Analysis!A22 -> Jan-2024 | H14: =Summary_Analysis!B22 -> 4785.91
A15: =Summary_Analysis!A6 -> South | B15: =Summary_Analysis!B6 -> 12192.13 | D15: =Summary_Analysis!A15 -> Furniture | E15: =Summary_Analysis!B15 -> 30998.36 | G15: =Summary_Analysis!A23 -> Feb-2024 | H15: =Summary_Analysis!B23 -> 6279.09
A16: =Summary_Analysis!A7 -> East | B16: =Summary_Analysis!B7 -> 10840.84 | D16: =Summary_Analysis!A16 -> Stationery | E16: =Summary_Analysis!B16 -> 4798.89 | G16: =Summary_Analysis!A24 -> Mar-2024 | H16: =Summary_Analysis!B24 -> 4719.04
A17: =Summary_Analysis!A8 -> West | B17: =Summary_Analysis!B8 -> 13643.61 | D17: =Summary_Analysis!A17 -> Apparel | E17: =Summary_Analysis!B17 -> 16612.64 | G17: =Summary_Analysis!A25 -> Apr-2024 | H17: =Summary_Analysis!B25 -> 4198.48
A18: =Summary_Analysis!A9 -> Central | B18: =Summary_Analysis!B9 -> 12435.63 | G18: =Summary_Analysis!A26 -> May-2024 | H18: =Summary_Analysis!B26 -> 4189.11
G19: =Summary_Analysis!A27 -> Jun-2024 | H19: =Summary_Analysis!B27 -> 6150.22
G20: =Summary_Analysis!A28 -> Jul-2024 | H20: =Summary_Analysis!B28 -> 4279.26
G21: =Summary_Analysis!A29 -> Aug-2024 | H21: =Summary_Analysis!B29 -> 5068.45
G22: =Summary_Analysis!A30 -> Sep-2024 | H22: =Summary_Analysis!B30 -> 7371.42
G23: =Summary_Analysis!A31 -> Oct-2024 | H23: =Summary_Analysis!B31 -> 4600.5
G24: =Summary_Analysis!A32 -> Nov-2024 | H24: =Summary_Analysis!B32 -> 6127.85
G25: =Summary_Analysis!A33 -> Dec-2024 | H25: =Summary_Analysis!B33 -> 4169.45
